/*      */ package com.pla.annoyingvillagers.gameasset;
/*      */ 
/*      */ import com.pla.annoyingvillagers.block.ObsidianBlock;
/*      */ import com.pla.annoyingvillagers.block.ShadowObsidianBlock;
/*      */ import com.pla.annoyingvillagers.clazz.TridentMode;
/*      */ import com.pla.annoyingvillagers.entity.BlockProjectileEntity;
/*      */ import com.pla.annoyingvillagers.entity.BlueDemonThrownTridentEntity;
/*      */ import com.pla.annoyingvillagers.init.AnnoyingVillagersModBlocks;
/*      */ import com.pla.annoyingvillagers.init.AnnoyingVillagersModParticleTypes;
/*      */ import com.pla.annoyingvillagers.init.AnnoyingVillagersModSounds;
/*      */ import com.pla.annoyingvillagers.item.BlueDemonTridentItem;
/*      */ import com.pla.annoyingvillagers.task.DelayedTask;
/*      */ import com.pla.annoyingvillagers.util.EpicfightUtil;
/*      */ import com.pla.annoyingvillagers.util.HerobrineUtil;
/*      */ import com.pla.annoyingvillagers.util.ShockwaveUtil;
/*      */ import java.util.Random;
/*      */ import net.minecraft.core.BlockPos;
/*      */ import net.minecraft.core.Position;
/*      */ import net.minecraft.core.Vec3i;
/*      */ import net.minecraft.core.particles.ParticleOptions;
/*      */ import net.minecraft.server.level.ServerLevel;
/*      */ import net.minecraft.sounds.SoundEvent;
/*      */ import net.minecraft.sounds.SoundEvents;
/*      */ import net.minecraft.sounds.SoundSource;
/*      */ import net.minecraft.util.Mth;
/*      */ import net.minecraft.world.InteractionHand;
/*      */ import net.minecraft.world.entity.Entity;
/*      */ import net.minecraft.world.entity.LivingEntity;
/*      */ import net.minecraft.world.entity.Mob;
/*      */ import net.minecraft.world.entity.player.Player;
/*      */ import net.minecraft.world.entity.projectile.AbstractArrow;
/*      */ import net.minecraft.world.item.Item;
/*      */ import net.minecraft.world.item.ItemStack;
/*      */ import net.minecraft.world.level.Level;
/*      */ import net.minecraft.world.level.block.Block;
/*      */ import net.minecraft.world.level.block.Blocks;
/*      */ import net.minecraft.world.level.block.state.BlockState;
/*      */ import net.minecraft.world.level.block.state.properties.BlockStateProperties;
/*      */ import net.minecraft.world.level.block.state.properties.Property;
/*      */ import net.minecraft.world.phys.Vec3;
/*      */ import yesman.epicfight.api.animation.Joint;
/*      */ import yesman.epicfight.api.animation.property.AnimationEvent;
/*      */ import yesman.epicfight.api.animation.property.AnimationParameters;
/*      */ import yesman.epicfight.api.asset.AssetAccessor;
/*      */ import yesman.epicfight.api.utils.math.OpenMatrix4f;
/*      */ import yesman.epicfight.api.utils.math.Vec3f;
/*      */ import yesman.epicfight.gameasset.Armatures;
/*      */ import yesman.epicfight.gameasset.EpicFightSounds;
/*      */ import yesman.epicfight.model.armature.HumanoidArmature;
/*      */ import yesman.epicfight.world.capabilities.entitypatch.LivingEntityPatch;
/*      */ 
/*      */ 
/*      */ 
/*      */ 
/*      */ 
/*      */ 
/*      */ 
/*      */ 
/*      */ 
/*      */ 
/*      */ 
/*      */ 
/*      */ 
/*      */ 
/*      */ 
/*      */ 
/*      */ 
/*      */ 
/*      */ 
/*      */ 
/*      */ 
/*      */ 
/*      */ 
/*      */ 
/*      */ 
/*      */ 
/*      */ 
/*      */ 
/*      */ 
/*      */ 
/*      */ 
/*      */ 
/*      */ 
/*      */ 
/*      */ 
/*      */ 
/*      */ 
/*      */ 
/*      */ 
/*      */ 
/*      */ 
/*      */ 
/*      */ 
/*      */ 
/*      */ 
/*      */ 
/*      */ 
/*      */ 
/*      */ 
/*      */ 
/*      */ 
/*      */ 
/*      */ 
/*      */ 
/*      */ 
/*      */ 
/*      */ 
/*      */ 
/*      */ 
/*      */ 
/*      */ 
/*      */ 
/*      */ 
/*      */ 
/*      */ 
/*      */ 
/*      */ 
/*      */ 
/*      */ 
/*      */ 
/*      */ 
/*      */ 
/*      */ 
/*      */ 
/*      */ 
/*      */ 
/*      */ 
/*      */ 
/*      */ 
/*      */ 
/*      */ 
/*      */ 
/*      */ 
/*      */ 
/*      */ 
/*      */ 
/*      */ 
/*      */ 
/*      */ 
/*      */ 
/*      */ 
/*      */ 
/*      */ 
/*      */ 
/*      */ 
/*      */ 
/*      */ 
/*      */ 
/*      */ 
/*      */ 
/*      */ 
/*      */ 
/*      */ 
/*      */ 
/*      */ 
/*      */ 
/*      */ 
/*      */ 
/*      */ 
/*      */ 
/*      */ 
/*      */ 
/*      */ 
/*      */ 
/*      */ 
/*      */ 
/*      */ 
/*      */ 
/*      */ 
/*      */ 
/*      */ 
/*      */ 
/*      */ 
/*      */ 
/*      */ 
/*      */ 
/*      */ 
/*      */ 
/*      */ 
/*      */ 
/*      */ 
/*      */ 
/*      */ 
/*      */ 
/*      */ 
/*      */ 
/*      */ 
/*      */ 
/*      */ 
/*      */ 
/*      */ 
/*      */ 
/*      */ 
/*      */ 
/*      */ 
/*      */ 
/*      */ 
/*      */ 
/*      */ 
/*      */ 
/*      */ 
/*      */ 
/*      */ 
/*      */ 
/*      */ 
/*      */ 
/*      */ 
/*      */ 
/*      */ 
/*      */ 
/*      */ 
/*      */ 
/*      */ 
/*      */ 
/*      */ 
/*      */ 
/*      */ 
/*      */ 
/*      */ 
/*      */ 
/*      */ 
/*      */ 
/*      */ 
/*      */ 
/*      */ 
/*      */ 
/*      */ 
/*      */ 
/*      */ 
/*      */ 
/*      */ 
/*      */ 
/*      */ 
/*      */ 
/*      */ 
/*      */ 
/*      */ 
/*      */ 
/*      */ 
/*      */ 
/*      */ 
/*      */ 
/*      */ 
/*      */ 
/*      */ 
/*      */ 
/*      */ 
/*      */ 
/*      */ 
/*      */ 
/*      */ 
/*      */ 
/*      */ 
/*      */ 
/*      */ 
/*      */ 
/*      */ 
/*      */ 
/*      */ 
/*      */ 
/*      */ 
/*      */ 
/*      */ 
/*      */ 
/*      */ 
/*      */ 
/*      */ 
/*      */ 
/*      */ 
/*      */ 
/*      */ 
/*      */ 
/*      */ 
/*      */ 
/*      */ 
/*      */ 
/*      */ 
/*      */ 
/*      */ 
/*      */ 
/*      */ 
/*      */ 
/*      */ 
/*      */ 
/*      */ 
/*      */ 
/*      */ 
/*      */ 
/*      */ 
/*      */ 
/*      */ 
/*      */ 
/*      */ 
/*      */ 
/*      */ 
/*      */ 
/*      */ 
/*      */ 
/*      */ 
/*      */ 
/*      */ 
/*      */ 
/*      */ 
/*      */ 
/*      */ 
/*      */ 
/*      */ 
/*      */ 
/*      */ 
/*      */ 
/*      */ 
/*      */ 
/*      */ 
/*      */ 
/*      */ 
/*      */ 
/*      */ 
/*      */ 
/*      */ 
/*      */ 
/*      */ 
/*      */ 
/*      */ 
/*      */ 
/*      */ 
/*      */ 
/*      */ 
/*      */ 
/*      */ 
/*      */ 
/*      */ 
/*      */ 
/*      */ 
/*      */ 
/*      */ 
/*      */ 
/*      */ 
/*      */ 
/*      */ 
/*      */ 
/*      */ 
/*      */ 
/*      */ 
/*      */ 
/*      */ 
/*      */ 
/*      */ 
/*      */ 
/*      */ 
/*      */ 
/*      */ 
/*      */ 
/*      */ 
/*      */ 
/*      */ 
/*      */ 
/*      */ 
/*      */ 
/*      */ 
/*      */ 
/*      */ 
/*      */ 
/*      */ 
/*      */ 
/*      */ 
/*      */ 
/*      */ 
/*      */ 
/*      */ 
/*      */ 
/*      */ 
/*      */ 
/*      */ 
/*      */ 
/*      */ 
/*      */ 
/*      */ 
/*      */ 
/*      */ 
/*      */ 
/*      */ 
/*      */ 
/*      */ 
/*      */ 
/*      */ 
/*      */ 
/*      */ 
/*      */ 
/*      */ 
/*      */ 
/*      */ 
/*      */ 
/*      */ 
/*      */ 
/*      */ 
/*      */ 
/*      */ 
/*      */ 
/*      */ 
/*      */ 
/*      */ 
/*      */ 
/*      */ 
/*      */ 
/*      */ 
/*      */ 
/*      */ 
/*      */ 
/*      */ 
/*      */ 
/*      */ 
/*      */ 
/*      */ 
/*      */ 
/*      */ 
/*      */ 
/*      */ 
/*      */ 
/*      */ 
/*      */ 
/*      */ 
/*      */ 
/*      */ 
/*      */ 
/*      */ 
/*      */ 
/*      */ 
/*      */ 
/*      */ 
/*      */ 
/*      */ 
/*      */ 
/*      */ 
/*      */ 
/*      */ 
/*      */ 
/*      */ 
/*      */ 
/*      */ 
/*      */ 
/*      */ 
/*      */ 
/*      */ 
/*      */ 
/*      */ 
/*      */ 
/*      */ 
/*      */ 
/*      */ 
/*      */ 
/*      */ 
/*      */ 
/*      */ 
/*      */ 
/*      */ 
/*      */ 
/*      */ 
/*      */ 
/*      */ 
/*      */ 
/*      */ 
/*      */ 
/*      */ 
/*      */ 
/*      */ 
/*      */ 
/*      */ 
/*      */ 
/*      */ 
/*      */ 
/*      */ 
/*      */ 
/*      */ 
/*      */ 
/*      */ 
/*      */ 
/*      */ 
/*      */ 
/*      */ 
/*      */ 
/*      */ 
/*      */ 
/*      */ 
/*      */ 
/*      */ 
/*      */ 
/*      */ 
/*      */ 
/*      */ 
/*      */ 
/*      */ 
/*      */ 
/*      */ 
/*      */ 
/*      */ 
/*      */ 
/*      */ 
/*      */ 
/*      */ 
/*      */ 
/*      */ 
/*      */ 
/*      */ 
/*      */ 
/*      */ 
/*      */ 
/*      */ 
/*      */ 
/*      */ 
/*      */ 
/*      */ 
/*      */ 
/*      */ 
/*      */ 
/*      */ 
/*      */ 
/*      */ 
/*      */ 
/*      */ 
/*      */ 
/*      */ 
/*      */ 
/*      */ 
/*      */ 
/*      */ 
/*      */ 
/*      */ 
/*      */ 
/*      */ 
/*      */ 
/*      */ 
/*      */ 
/*      */ 
/*      */ 
/*      */ 
/*      */ 
/*      */ 
/*      */ 
/*      */ 
/*      */ 
/*      */ 
/*      */ 
/*      */ 
/*      */ 
/*      */ 
/*      */ 
/*      */ 
/*      */ 
/*      */ 
/*      */ 
/*      */ 
/*      */ 
/*      */ 
/*      */ 
/*      */ 
/*      */ 
/*      */ 
/*      */ 
/*      */ 
/*      */ 
/*      */ 
/*      */ 
/*      */ 
/*      */ 
/*      */ 
/*      */ 
/*      */ 
/*      */ 
/*      */ 
/*      */ 
/*      */ 
/*      */ 
/*      */ 
/*      */ 
/*      */ 
/*      */ 
/*      */ 
/*      */ 
/*      */ 
/*      */ 
/*      */ 
/*      */ 
/*      */ 
/*      */ 
/*      */ 
/*      */ 
/*      */ 
/*      */ 
/*      */ 
/*      */ 
/*      */ 
/*      */ 
/*      */ 
/*      */ 
/*      */ 
/*      */ 
/*      */ 
/*      */ 
/*      */ 
/*      */ 
/*      */ 
/*      */ 
/*      */ 
/*      */ 
/*      */ 
/*      */ 
/*      */ 
/*      */ 
/*      */ 
/*      */ 
/*      */ 
/*      */ 
/*      */ 
/*      */ 
/*      */ 
/*      */ 
/*      */ 
/*      */ 
/*      */ 
/*      */ 
/*      */ 
/*      */ 
/*      */ 
/*      */ 
/*      */ 
/*      */ 
/*      */ 
/*      */ 
/*      */ 
/*      */ 
/*      */ 
/*      */ 
/*      */ 
/*      */ 
/*      */ 
/*      */ 
/*      */ 
/*      */ 
/*      */ 
/*      */ 
/*      */ 
/*      */ 
/*      */ 
/*      */ 
/*      */ 
/*      */ 
/*      */ 
/*      */ 
/*      */ 
/*      */ 
/*      */ 
/*      */ 
/*      */ 
/*      */ 
/*      */ 
/*      */ 
/*      */ 
/*      */ 
/*      */ 
/*      */ 
/*      */ 
/*      */ 
/*      */ 
/*      */ 
/*      */ 
/*      */ 
/*      */ 
/*      */ 
/*      */ 
/*      */ 
/*      */ 
/*      */ 
/*      */ 
/*      */ 
/*      */ 
/*      */ 
/*      */ 
/*      */ 
/*      */ 
/*      */ 
/*      */ 
/*      */ 
/*      */ 
/*      */ 
/*      */ 
/*      */ 
/*      */ 
/*      */ 
/*      */ 
/*      */ 
/*      */ 
/*      */ 
/*      */ 
/*      */ 
/*      */ 
/*      */ 
/*      */ 
/*      */ 
/*      */ 
/*      */ 
/*      */ 
/*      */ 
/*      */ 
/*      */ 
/*      */ 
/*      */ 
/*      */ 
/*      */ 
/*      */ 
/*      */ 
/*      */ 
/*      */ 
/*      */ 
/*      */ 
/*      */ 
/*      */ 
/*      */ 
/*      */ 
/*      */ 
/*      */ 
/*      */ 
/*      */ 
/*      */ 
/*      */ 
/*      */ 
/*      */ 
/*      */ 
/*      */ 
/*      */ 
/*      */ 
/*      */ 
/*      */ 
/*      */ 
/*      */ 
/*      */ 
/*      */ 
/*      */ 
/*      */ 
/*      */ 
/*      */ 
/*      */ 
/*      */ 
/*      */ 
/*      */ 
/*      */ 
/*      */ 
/*      */ 
/*      */ 
/*      */ 
/*      */ 
/*      */ 
/*      */ 
/*      */ 
/*      */ 
/*      */ 
/*      */ 
/*      */ 
/*      */ 
/*      */ 
/*      */ 
/*      */ 
/*      */ 
/*      */ 
/*      */ 
/*      */ 
/*      */ 
/*      */ 
/*      */ 
/*      */ 
/*      */ 
/*      */ 
/*      */ 
/*      */ 
/*      */ 
/*      */ 
/*      */ 
/*      */ 
/*      */ 
/*      */ 
/*      */ 
/*      */ 
/*      */ 
/*      */ 
/*      */ 
/*      */ 
/*      */ 
/*      */ 
/*      */ 
/*      */ 
/*      */ 
/*      */ 
/*      */ 
/*      */ 
/*      */ 
/*      */ 
/*      */ 
/*      */ 
/*      */ 
/*      */ 
/*      */ 
/*      */ 
/*      */ 
/*      */ 
/*      */ 
/*      */ 
/*      */ 
/*      */ 
/*      */ 
/*      */ 
/*      */ 
/*      */ 
/*      */ 
/*      */ 
/*      */ 
/*      */ 
/*      */ 
/*      */ 
/*      */ 
/*      */ 
/*      */ 
/*      */ 
/*      */ 
/*      */ 
/*      */ 
/*      */ 
/*      */ 
/*      */ 
/*      */ 
/*      */ 
/*      */ 
/*      */ 
/*      */ 
/*      */ 
/*      */ 
/*      */ 
/*      */ 
/*      */ 
/*      */ 
/*      */ 
/*      */ 
/*      */ 
/*      */ 
/*      */ 
/*      */ 
/*      */ 
/*      */ 
/*      */ 
/*      */ 
/*      */ 
/*      */ 
/*      */ 
/*      */ 
/*      */ 
/*      */ 
/*      */ 
/*      */ 
/*      */ 
/*      */ 
/*      */ 
/*      */ 
/*      */ 
/*      */ 
/*      */ 
/*      */ 
/*      */ 
/*      */ 
/*      */ 
/*      */ 
/*      */ 
/*      */ 
/*      */ 
/*      */ 
/*      */ 
/*      */ 
/*      */ 
/*      */ 
/*      */ 
/*      */ 
/*      */ 
/*      */ 
/*      */ 
/*      */ 
/*      */ 
/*      */ 
/*      */ 
/*      */ 
/*      */ 
/*      */ 
/*      */ 
/*      */ 
/*      */ 
/*      */ 
/*      */ 
/*      */ 
/*      */ 
/*      */ 
/*      */ 
/*      */ 
/*      */ 
/*      */ 
/*      */ 
/*      */ 
/*      */ 
/*      */ 
/*      */ 
/*      */ 
/*      */ 
/*      */ 
/*      */ 
/*      */ 
/*      */ 
/*      */ 
/*      */ 
/*      */ 
/*      */ 
/*      */ 
/*      */ 
/*      */ 
/*      */ 
/*      */ 
/*      */ 
/*      */ 
/*      */ 
/*      */ 
/*      */ 
/*      */ 
/*      */ 
/*      */ 
/*      */ 
/*      */ 
/*      */ 
/*      */ 
/*      */ 
/*      */ 
/*      */ 
/*      */ 
/*      */ 
/*      */ 
/*      */ 
/*      */ 
/*      */ 
/*      */ 
/*      */ 
/*      */ 
/*      */ 
/*      */ 
/*      */ 
/*      */ 
/*      */ 
/*      */ 
/*      */ 
/*      */ 
/*      */ 
/*      */ 
/*      */ 
/*      */ 
/*      */ 
/*      */ 
/*      */ 
/*      */ 
/*      */ 
/*      */ 
/*      */ 
/*      */ 
/*      */ 
/*      */ 
/*      */ 
/*      */ 
/*      */ 
/*      */ 
/*      */ 
/*      */ 
/*      */ 
/*      */ 
/*      */ 
/*      */ 
/*      */ 
/*      */ 
/*      */ 
/*      */ 
/*      */ 
/*      */ 
/*      */ 
/*      */ 
/*      */ 
/*      */ 
/*      */ 
/*      */ 
/*      */ 
/*      */ 
/*      */ 
/*      */ 
/*      */ 
/*      */ 
/*      */ 
/*      */ 
/*      */ 
/*      */ 
/*      */ 
/*      */ 
/*      */ 
/*      */ 
/*      */ 
/*      */ 
/*      */ 
/*      */ 
/*      */ 
/*      */ 
/*      */ 
/*      */ 
/*      */ 
/*      */ 
/*      */ 
/*      */ 
/*      */ 
/*      */ 
/*      */ 
/*      */ 
/*      */ 
/*      */ 
/*      */ 
/*      */ 
/*      */ 
/*      */ 
/*      */ 
/*      */ 
/*      */ 
/*      */ 
/*      */ 
/*      */ 
/*      */ 
/*      */ 
/*      */ 
/*      */ 
/*      */ 
/*      */ 
/*      */ 
/*      */ 
/*      */ 
/*      */ 
/*      */ 
/*      */ 
/*      */ 
/*      */ 
/*      */ 
/*      */ 
/*      */ 
/*      */ 
/*      */ 
/*      */ 
/*      */ 
/*      */ 
/*      */ 
/*      */ 
/*      */ 
/*      */ 
/*      */ 
/*      */ 
/*      */ 
/*      */ 
/*      */ 
/*      */ 
/*      */ 
/*      */ 
/*      */ 
/*      */ 
/*      */ 
/*      */ 
/*      */ 
/*      */ 
/*      */ 
/*      */ 
/*      */ 
/*      */ 
/*      */ 
/*      */ 
/*      */ 
/*      */ 
/*      */ 
/*      */ 
/*      */ 
/*      */ 
/*      */ 
/*      */ 
/*      */ 
/*      */ 
/*      */ 
/*      */ 
/*      */ 
/*      */ 
/*      */ 
/*      */ 
/*      */ 
/*      */ 
/*      */ 
/*      */ 
/*      */ 
/*      */ 
/*      */ 
/*      */ 
/*      */ 
/*      */ 
/*      */ 
/*      */ 
/*      */ 
/*      */ 
/*      */ 
/*      */ 
/*      */ 
/*      */ 
/*      */ 
/*      */ 
/*      */ 
/*      */ 
/*      */ 
/*      */ 
/*      */ 
/*      */ 
/*      */ 
/*      */ 
/*      */ 
/*      */ 
/*      */ 
/*      */ 
/*      */ 
/*      */ 
/*      */ 
/*      */ 
/*      */ 
/*      */ 
/*      */ 
/*      */ 
/*      */ 
/*      */ 
/*      */ 
/*      */ 
/*      */ 
/*      */ 
/*      */ 
/*      */ 
/*      */ 
/*      */ 
/*      */ 
/*      */ 
/*      */ 
/*      */ 
/*      */ 
/*      */ 
/*      */ 
/*      */ 
/*      */ 
/*      */ 
/*      */ 
/*      */ 
/*      */ 
/*      */ 
/*      */ 
/*      */ 
/*      */ 
/*      */ 
/*      */ 
/*      */ 
/*      */ 
/*      */ 
/*      */ 
/*      */ 
/*      */ 
/*      */ 
/*      */ 
/*      */ 
/*      */ 
/*      */ 
/*      */ 
/*      */ 
/*      */ 
/*      */ 
/*      */ 
/*      */ 
/*      */ 
/*      */ 
/*      */ 
/*      */ 
/*      */ 
/*      */ 
/*      */ 
/*      */ 
/*      */ 
/*      */ 
/*      */ 
/*      */ 
/*      */ 
/*      */ 
/*      */ 
/*      */ 
/*      */ 
/*      */ 
/*      */ 
/*      */ 
/*      */ 
/*      */ 
/*      */ 
/*      */ 
/*      */ 
/*      */ 
/*      */ 
/*      */ 
/*      */ 
/*      */ 
/*      */ 
/*      */ 
/*      */ 
/*      */ 
/*      */ 
/*      */ 
/*      */ 
/*      */ 
/*      */ 
/*      */ 
/*      */ 
/*      */ 
/*      */ 
/*      */ 
/*      */ 
/*      */ 
/*      */ 
/*      */ 
/*      */ 
/*      */ 
/*      */ 
/*      */ 
/*      */ 
/*      */ 
/*      */ 
/*      */ 
/*      */ 
/*      */ 
/*      */ 
/*      */ 
/*      */ 
/*      */ 
/*      */ 
/*      */ 
/*      */ 
/*      */ 
/*      */ 
/*      */ 
/*      */ 
/*      */ 
/*      */ 
/*      */ 
/*      */ 
/*      */ 
/*      */ 
/*      */ 
/*      */ 
/*      */ 
/*      */ 
/*      */ 
/*      */ 
/*      */ 
/*      */ 
/*      */ 
/*      */ 
/*      */ 
/*      */ 
/*      */ 
/*      */ 
/*      */ 
/*      */ 
/*      */ 
/*      */ 
/*      */ 
/*      */ 
/*      */ 
/*      */ 
/*      */ 
/*      */ 
/*      */ 
/*      */ 
/*      */ 
/*      */ 
/*      */ 
/*      */ 
/*      */ 
/*      */ 
/*      */ 
/*      */ 
/*      */ 
/*      */ 
/*      */ 
/*      */ 
/*      */ 
/*      */ 
/*      */ 
/*      */ 
/*      */ 
/*      */ 
/*      */ 
/*      */ 
/*      */ 
/*      */ 
/*      */ 
/*      */ 
/*      */ 
/*      */ 
/*      */ 
/*      */ 
/*      */ 
/*      */ 
/*      */ 
/*      */ 
/*      */ 
/*      */ 
/*      */ 
/*      */ 
/*      */ 
/*      */ 
/*      */ 
/*      */ 
/*      */ 
/*      */ 
/*      */ 
/*      */ 
/*      */ 
/*      */ 
/*      */ 
/*      */ 
/*      */ 
/*      */ 
/*      */ 
/*      */ 
/*      */ 
/*      */ 
/*      */ 
/*      */ 
/*      */ 
/*      */ 
/*      */ 
/*      */ 
/*      */ 
/*      */ 
/*      */ 
/*      */ 
/*      */ 
/*      */ 
/*      */ 
/*      */ 
/*      */ 
/*      */ 
/*      */ 
/*      */ 
/*      */ 
/*      */ 
/*      */ 
/*      */ 
/*      */ 
/*      */ 
/*      */ 
/*      */ 
/*      */ 
/*      */ 
/*      */ 
/*      */ 
/*      */ 
/*      */ 
/*      */ 
/*      */ 
/*      */ 
/*      */ 
/*      */ 
/*      */ 
/*      */ 
/*      */ 
/*      */ 
/*      */ 
/*      */ 
/*      */ 
/*      */ 
/*      */ 
/*      */ 
/*      */ 
/*      */ 
/*      */ 
/*      */ 
/*      */ 
/*      */ 
/*      */ 
/*      */ 
/*      */ 
/*      */ 
/*      */ 
/*      */ 
/*      */ 
/*      */ 
/*      */ 
/*      */ 
/*      */ 
/*      */ 
/*      */ 
/*      */ 
/*      */ 
/*      */ 
/*      */ 
/*      */ 
/*      */ 
/*      */ 
/*      */ 
/*      */ 
/*      */ 
/*      */ 
/*      */ 
/*      */ 
/*      */ 
/*      */ 
/*      */ 
/*      */ 
/*      */ 
/*      */ 
/*      */ 
/*      */ 
/*      */ 
/*      */ 
/*      */ 
/*      */ 
/*      */ 
/*      */ 
/*      */ 
/*      */ 
/*      */ 
/*      */ 
/*      */ 
/*      */ 
/*      */ 
/*      */ 
/*      */ 
/*      */ 
/*      */ 
/*      */ 
/*      */ 
/*      */ 
/*      */ 
/*      */ 
/*      */ 
/*      */ 
/*      */ 
/*      */ 
/*      */ 
/*      */ 
/*      */ 
/*      */ 
/*      */ 
/*      */ 
/*      */ 
/*      */ 
/*      */ 
/*      */ 
/*      */ 
/*      */ 
/*      */ 
/*      */ 
/*      */ 
/*      */ 
/*      */ 
/*      */ 
/*      */ 
/*      */ 
/*      */ 
/*      */ 
/*      */ 
/*      */ 
/*      */ 
/*      */ 
/*      */ 
/*      */ 
/*      */ 
/*      */ 
/*      */ 
/*      */ 
/*      */ 
/*      */ 
/*      */ 
/*      */ 
/*      */ 
/*      */ 
/*      */ 
/*      */ 
/*      */ 
/*      */ 
/*      */ 
/*      */ 
/*      */ 
/*      */ 
/*      */ 
/*      */ 
/*      */ 
/*      */ 
/*      */ 
/*      */ 
/*      */ 
/*      */ 
/*      */ 
/*      */ 
/*      */ 
/*      */ 
/*      */ 
/*      */ 
/*      */ 
/*      */ 
/*      */ 
/*      */ 
/*      */ 
/*      */ 
/*      */ 
/*      */ 
/*      */ 
/*      */ 
/*      */ 
/*      */ 
/*      */ 
/*      */ 
/*      */ 
/*      */ 
/*      */ 
/*      */ 
/*      */ 
/*      */ 
/*      */ 
/*      */ 
/*      */ 
/*      */ 
/*      */ 
/*      */ 
/*      */ 
/*      */ 
/*      */ 
/*      */ 
/*      */ 
/*      */ 
/*      */ 
/*      */ 
/*      */ 
/*      */ 
/*      */ 
/*      */ 
/*      */ 
/*      */ 
/*      */ 
/*      */ 
/*      */ 
/*      */ 
/*      */ 
/*      */ 
/*      */ 
/*      */ 
/*      */ 
/*      */ 
/*      */ 
/*      */ 
/*      */ 
/*      */ 
/*      */ 
/*      */ 
/*      */ 
/*      */ 
/*      */ 
/*      */ 
/*      */ 
/*      */ 
/*      */ 
/*      */ 
/*      */ 
/*      */ 
/*      */ 
/*      */ 
/*      */ 
/*      */ 
/*      */ 
/*      */ 
/*      */ 
/*      */ 
/*      */ 
/*      */ 
/*      */ 
/*      */ 
/*      */ 
/*      */ 
/*      */ 
/*      */ 
/*      */ 
/*      */ 
/*      */ 
/*      */ 
/*      */ 
/*      */ 
/*      */ 
/*      */ 
/*      */ 
/*      */ 
/*      */ 
/*      */ 
/*      */ 
/*      */ 
/*      */ 
/*      */ 
/*      */ 
/*      */ 
/*      */ 
/*      */ 
/*      */ 
/*      */ 
/*      */ 
/*      */ 
/*      */ 
/*      */ 
/*      */ 
/*      */ 
/*      */ 
/*      */ 
/*      */ 
/*      */ 
/*      */ 
/*      */ 
/*      */ 
/*      */ 
/*      */ 
/*      */ 
/*      */ 
/*      */ 
/*      */ 
/*      */ 
/*      */ 
/*      */ 
/*      */ 
/*      */ 
/*      */ 
/*      */ 
/*      */ 
/*      */ 
/*      */ 
/*      */ 
/*      */ 
/*      */ 
/*      */ 
/*      */ 
/*      */ 
/*      */ 
/*      */ 
/*      */ 
/*      */ 
/*      */ 
/*      */ 
/*      */ 
/*      */ 
/*      */ 
/*      */ 
/*      */ 
/*      */ 
/*      */ 
/*      */ 
/*      */ 
/*      */ 
/*      */ 
/*      */ 
/*      */ 
/*      */ 
/*      */ 
/*      */ 
/*      */ 
/*      */ 
/*      */ 
/*      */ 
/*      */ 
/*      */ 
/*      */ 
/*      */ 
/*      */ 
/*      */ 
/*      */ 
/*      */ 
/*      */ 
/*      */ 
/*      */ 
/*      */ 
/*      */ 
/*      */ 
/*      */ 
/*      */ 
/*      */ 
/*      */ 
/*      */ 
/*      */ 
/*      */ 
/*      */ 
/*      */ 
/*      */ 
/*      */ 
/*      */ 
/*      */ 
/*      */ 
/*      */ 
/*      */ 
/*      */ 
/*      */ 
/*      */ 
/*      */ 
/*      */ 
/*      */ 
/*      */ 
/*      */ 
/*      */ 
/*      */ 
/*      */ 
/*      */ 
/*      */ 
/*      */ 
/*      */ 
/*      */ 
/*      */ 
/*      */ 
/*      */ 
/*      */ 
/*      */ 
/*      */ 
/*      */ 
/*      */ 
/*      */ 
/*      */ 
/*      */ 
/*      */ 
/*      */ 
/*      */ 
/*      */ 
/*      */ 
/*      */ 
/*      */ 
/*      */ 
/*      */ 
/*      */ 
/*      */ 
/*      */ 
/*      */ 
/*      */ 
/*      */ 
/*      */ 
/*      */ 
/*      */ 
/*      */ 
/*      */ 
/*      */ 
/*      */ 
/*      */ 
/*      */ 
/*      */ 
/*      */ 
/*      */ 
/*      */ 
/*      */ 
/*      */ 
/*      */ 
/*      */ 
/*      */ 
/*      */ 
/*      */ 
/*      */ 
/*      */ 
/*      */ 
/*      */ 
/*      */ 
/*      */ 
/*      */ 
/*      */ 
/*      */ 
/*      */ 
/*      */ 
/*      */ 
/*      */ 
/*      */ 
/*      */ 
/*      */ 
/*      */ 
/*      */ 
/*      */ 
/*      */ 
/*      */ 
/*      */ 
/*      */ 
/*      */ 
/*      */ 
/*      */ 
/*      */ 
/*      */ 
/*      */ 
/*      */ 
/*      */ 
/*      */ 
/*      */ 
/*      */ 
/*      */ 
/*      */ 
/*      */ 
/*      */ 
/*      */ 
/*      */ 
/*      */ 
/*      */ 
/*      */ 
/*      */ 
/*      */ 
/*      */ 
/*      */ 
/*      */ 
/*      */ 
/*      */ 
/*      */ 
/*      */ 
/*      */ 
/*      */ 
/*      */ 
/*      */ 
/*      */ 
/*      */ 
/*      */ 
/*      */ 
/*      */ 
/*      */ 
/*      */ 
/*      */ 
/*      */ 
/*      */ 
/*      */ 
/*      */ 
/*      */ 
/*      */ 
/*      */ 
/*      */ 
/*      */ 
/*      */ 
/*      */ 
/*      */ 
/*      */ 
/*      */ 
/*      */ 
/*      */ 
/*      */ 
/*      */ 
/*      */ 
/*      */ 
/*      */ 
/*      */ 
/*      */ 
/*      */ 
/*      */ 
/*      */ 
/*      */ 
/*      */ 
/*      */ 
/*      */ 
/*      */ 
/*      */ 
/*      */ 
/*      */ 
/*      */ 
/*      */ 
/*      */ 
/*      */ 
/*      */ 
/*      */ 
/*      */ 
/*      */ 
/*      */ 
/*      */ 
/*      */ 
/*      */ 
/*      */ 
/*      */ 
/*      */ 
/*      */ 
/*      */ 
/*      */ 
/*      */ 
/*      */ 
/*      */ 
/*      */ 
/*      */ 
/*      */ 
/*      */ 
/*      */ 
/*      */ 
/*      */ 
/*      */ 
/*      */ 
/*      */ 
/*      */ 
/*      */ 
/*      */ 
/*      */ 
/*      */ 
/*      */ 
/*      */ 
/*      */ 
/*      */ 
/*      */ 
/*      */ 
/*      */ 
/*      */ 
/*      */ 
/*      */ 
/*      */ 
/*      */ 
/*      */ 
/*      */ 
/*      */ 
/*      */ 
/*      */ 
/*      */ 
/*      */ 
/*      */ 
/*      */ 
/*      */ 
/*      */ 
/*      */ 
/*      */ 
/*      */ 
/*      */ 
/*      */ 
/*      */ 
/*      */ 
/*      */ 
/*      */ 
/*      */ 
/*      */ 
/*      */ 
/*      */ 
/*      */ 
/*      */ 
/*      */ 
/*      */ 
/*      */ 
/*      */ 
/*      */ 
/*      */ 
/*      */ 
/*      */ 
/*      */ 
/*      */ 
/*      */ 
/*      */ 
/*      */ 
/*      */ 
/*      */ 
/*      */ 
/*      */ 
/*      */ 
/*      */ 
/*      */ 
/*      */ 
/*      */ 
/*      */ 
/*      */ 
/*      */ 
/*      */ 
/*      */ 
/*      */ 
/*      */ 
/*      */ 
/*      */ 
/*      */ 
/*      */ 
/*      */ 
/*      */ 
/*      */ 
/*      */ 
/*      */ 
/*      */ 
/*      */ 
/*      */ 
/*      */ 
/*      */ 
/*      */ 
/*      */ 
/*      */ 
/*      */ 
/*      */ 
/*      */ 
/*      */ 
/*      */ 
/*      */ 
/*      */ 
/*      */ 
/*      */ 
/*      */ 
/*      */ 
/*      */ 
/*      */ 
/*      */ 
/*      */ 
/*      */ 
/*      */ 
/*      */ 
/*      */ 
/*      */ 
/*      */ 
/*      */ 
/*      */ 
/*      */ 
/*      */ 
/*      */ 
/*      */ 
/*      */ 
/*      */ 
/*      */ 
/*      */ 
/*      */ 
/*      */ 
/*      */ 
/*      */ 
/*      */ 
/*      */ 
/*      */ 
/*      */ 
/*      */ 
/*      */ 
/*      */ 
/*      */ 
/*      */ 
/*      */ 
/*      */ 
/*      */ 
/*      */ 
/*      */ 
/*      */ 
/*      */ 
/*      */ 
/*      */ 
/*      */ 
/*      */ 
/*      */ 
/*      */ 
/*      */ 
/*      */ 
/*      */ 
/*      */ 
/*      */ 
/*      */ 
/*      */ 
/*      */ 
/*      */ 
/*      */ 
/*      */ 
/*      */ 
/*      */ 
/*      */ 
/*      */ 
/*      */ 
/*      */ 
/*      */ 
/*      */ 
/*      */ 
/*      */ 
/*      */ 
/*      */ 
/*      */ 
/*      */ 
/*      */ 
/*      */ 
/*      */ 
/*      */ 
/*      */ 
/*      */ 
/*      */ 
/*      */ 
/*      */ 
/*      */ 
/*      */ 
/*      */ 
/*      */ 
/*      */ 
/*      */ 
/*      */ 
/*      */ 
/*      */ 
/*      */ 
/*      */ 
/*      */ 
/*      */ 
/*      */ 
/*      */ 
/*      */ 
/*      */ 
/*      */ 
/*      */ 
/*      */ 
/*      */ 
/*      */ 
/*      */ 
/*      */ 
/*      */ 
/*      */ 
/*      */ 
/*      */ 
/*      */ 
/*      */ 
/*      */ 
/*      */ 
/*      */ 
/*      */ 
/*      */ 
/*      */ 
/*      */ 
/*      */ 
/*      */ 
/*      */ 
/*      */ 
/*      */ 
/*      */ 
/*      */ 
/*      */ 
/*      */ 
/*      */ 
/*      */ 
/*      */ 
/*      */ 
/*      */ 
/*      */ 
/*      */ 
/*      */ 
/*      */ 
/*      */ 
/*      */ 
/*      */ 
/*      */ 
/*      */ 
/*      */ 
/*      */ 
/*      */ 
/*      */ 
/*      */ 
/*      */ 
/*      */ 
/*      */ 
/*      */ 
/*      */ 
/*      */ 
/*      */ 
/*      */ 
/*      */ 
/*      */ 
/*      */ 
/*      */ 
/*      */ 
/*      */ 
/*      */ 
/*      */ 
/*      */ 
/*      */ 
/*      */ 
/*      */ 
/*      */ 
/*      */ 
/*      */ 
/*      */ 
/*      */ 
/*      */ 
/*      */ 
/*      */ 
/*      */ 
/*      */ 
/*      */ 
/*      */ 
/*      */ 
/*      */ 
/*      */ 
/*      */ 
/*      */ 
/*      */ 
/*      */ 
/*      */ 
/*      */ 
/*      */ 
/*      */ 
/*      */ 
/*      */ 
/*      */ 
/*      */ 
/*      */ 
/*      */ 
/*      */ 
/*      */ 
/*      */ 
/*      */ 
/*      */ 
/*      */ 
/*      */ 
/*      */ 
/*      */ 
/*      */ 
/*      */ 
/*      */ 
/*      */ 
/*      */ 
/*      */ 
/*      */ 
/*      */ 
/*      */ 
/*      */ 
/*      */ 
/*      */ 
/*      */ 
/*      */ 
/*      */ 
/*      */ 
/*      */ 
/*      */ 
/*      */ 
/*      */ 
/*      */ 
/*      */ 
/*      */ 
/*      */ 
/*      */ 
/*      */ 
/*      */ 
/*      */ 
/*      */ 
/*      */ 
/*      */ 
/*      */ 
/*      */ 
/*      */ 
/*      */ 
/*      */ 
/*      */ 
/*      */ 
/*      */ 
/*      */ 
/*      */ 
/*      */ 
/*      */ 
/*      */ 
/*      */ 
/*      */ 
/*      */ 
/*      */ 
/*      */ 
/*      */ 
/*      */ 
/*      */ 
/*      */ 
/*      */ 
/*      */ 
/*      */ 
/*      */ 
/*      */ 
/*      */ 
/*      */ 
/*      */ 
/*      */ 
/*      */ 
/*      */ 
/*      */ 
/*      */ 
/*      */ 
/*      */ 
/*      */ 
/*      */ 
/*      */ 
/*      */ 
/*      */ 
/*      */ 
/*      */ 
/*      */ 
/*      */ 
/*      */ 
/*      */ 
/*      */ 
/*      */ 
/*      */ 
/*      */ 
/*      */ 
/*      */ 
/*      */ 
/*      */ 
/*      */ 
/*      */ 
/*      */ 
/*      */ 
/*      */ 
/*      */ 
/*      */ 
/*      */ 
/*      */ 
/*      */ 
/*      */ 
/*      */ 
/*      */ 
/*      */ 
/*      */ 
/*      */ 
/*      */ 
/*      */ 
/*      */ 
/*      */ 
/*      */ 
/*      */ 
/*      */ 
/*      */ 
/*      */ 
/*      */ 
/*      */ 
/*      */ 
/*      */ 
/*      */ 
/*      */ 
/*      */ 
/*      */ 
/*      */ 
/*      */ 
/*      */ 
/*      */ 
/*      */ 
/*      */ 
/*      */ 
/*      */ 
/*      */ 
/*      */ 
/*      */ 
/*      */ 
/*      */ 
/*      */ 
/*      */ 
/*      */ 
/*      */ 
/*      */ 
/*      */ 
/*      */ 
/*      */ 
/*      */ 
/*      */ 
/*      */ 
/*      */ 
/*      */ 
/*      */ 
/*      */ 
/*      */ 
/*      */ 
/*      */ 
/*      */ 
/*      */ 
/*      */ 
/*      */ 
/*      */ 
/*      */ 
/*      */ 
/*      */ 
/*      */ 
/*      */ 
/*      */ 
/*      */ 
/*      */ 
/*      */ 
/*      */ 
/*      */ 
/*      */ 
/*      */ 
/*      */ 
/*      */ 
/*      */ 
/*      */ 
/*      */ 
/*      */ 
/*      */ 
/*      */ 
/*      */ 
/*      */ 
/*      */ 
/*      */ 
/*      */ 
/*      */ 
/*      */ 
/*      */ 
/*      */ 
/*      */ 
/*      */ 
/*      */ 
/*      */ 
/*      */ 
/*      */ 
/*      */ 
/*      */ 
/*      */ 
/*      */ 
/*      */ 
/*      */ 
/*      */ 
/*      */ 
/*      */ 
/*      */ 
/*      */ 
/*      */ 
/*      */ 
/*      */ 
/*      */ 
/*      */ 
/*      */ 
/*      */ 
/*      */ 
/*      */ 
/*      */ 
/*      */ 
/*      */ 
/*      */ 
/*      */ 
/*      */ 
/*      */ 
/*      */ 
/*      */ 
/*      */ 
/*      */ 
/*      */ 
/*      */ 
/*      */ 
/*      */ 
/*      */ 
/*      */ 
/*      */ 
/*      */ 
/*      */ 
/*      */ 
/*      */ 
/*      */ 
/*      */ 
/*      */ 
/*      */ 
/*      */ 
/*      */ 
/*      */ 
/*      */ 
/*      */ 
/*      */ 
/*      */ 
/*      */ 
/*      */ 
/*      */ 
/*      */ 
/*      */ 
/*      */ 
/*      */ 
/*      */ 
/*      */ 
/*      */ 
/*      */ 
/*      */ 
/*      */ 
/*      */ 
/*      */ 
/*      */ 
/*      */ 
/*      */ 
/*      */ 
/*      */ 
/*      */ 
/*      */ 
/*      */ 
/*      */ 
/*      */ 
/*      */ 
/*      */ 
/*      */ 
/*      */ 
/*      */ 
/*      */ 
/*      */ 
/*      */ 
/*      */ 
/*      */ 
/*      */ 
/*      */ 
/*      */ 
/*      */ 
/*      */ 
/*      */ 
/*      */ 
/*      */ 
/*      */ 
/*      */ 
/*      */ 
/*      */ 
/*      */ 
/*      */ 
/*      */ 
/*      */ 
/*      */ 
/*      */ 
/*      */ 
/*      */ 
/*      */ 
/*      */ 
/*      */ 
/*      */ 
/*      */ 
/*      */ 
/*      */ 
/*      */ 
/*      */ 
/*      */ 
/*      */ 
/*      */ 
/*      */ 
/*      */ 
/*      */ 
/*      */ 
/*      */ 
/*      */ 
/*      */ 
/*      */ 
/*      */ 
/*      */ 
/*      */ 
/*      */ 
/*      */ 
/*      */ 
/*      */ 
/*      */ 
/*      */ 
/*      */ 
/*      */ 
/*      */ 
/*      */ 
/*      */ 
/*      */ 
/*      */ 
/*      */ 
/*      */ 
/*      */ 
/*      */ 
/*      */ 
/*      */ 
/*      */ 
/*      */ 
/*      */ 
/*      */ 
/*      */ 
/*      */ 
/*      */ 
/*      */ 
/*      */ 
/*      */ 
/*      */ 
/*      */ 
/*      */ 
/*      */ 
/*      */ 
/*      */ 
/*      */ 
/*      */ 
/*      */ 
/*      */ 
/*      */ 
/*      */ 
/*      */ 
/*      */ 
/*      */ 
/*      */ 
/*      */ 
/*      */ 
/*      */ 
/*      */ 
/*      */ 
/*      */ 
/*      */ 
/*      */ 
/*      */ 
/*      */ 
/*      */ 
/*      */ 
/*      */ 
/*      */ 
/*      */ 
/*      */ 
/*      */ 
/*      */ 
/*      */ 
/*      */ 
/*      */ 
/*      */ 
/*      */ 
/*      */ 
/*      */ 
/*      */ 
/*      */ 
/*      */ 
/*      */ 
/*      */ 
/*      */ 
/*      */ 
/*      */ 
/*      */ 
/*      */ 
/*      */ 
/*      */ 
/*      */ 
/*      */ 
/*      */ 
/*      */ 
/*      */ 
/*      */ 
/*      */ 
/*      */ 
/*      */ 
/*      */ 
/*      */ 
/*      */ 
/*      */ 
/*      */ 
/*      */ 
/*      */ 
/*      */ 
/*      */ 
/*      */ 
/*      */ 
/*      */ 
/*      */ 
/*      */ 
/*      */ 
/*      */ 
/*      */ 
/*      */ 
/*      */ 
/*      */ 
/*      */ 
/*      */ 
/*      */ 
/*      */ 
/*      */ 
/*      */ 
/*      */ 
/*      */ 
/*      */ 
/*      */ 
/*      */ 
/*      */ 
/*      */ 
/*      */ 
/*      */ 
/*      */ 
/*      */ 
/*      */ 
/*      */ 
/*      */ 
/*      */ 
/*      */ 
/*      */ 
/*      */ 
/*      */ 
/*      */ 
/*      */ 
/*      */ 
/*      */ 
/*      */ 
/*      */ 
/*      */ 
/*      */ 
/*      */ 
/*      */ 
/*      */ 
/*      */ 
/*      */ 
/*      */ 
/*      */ 
/*      */ 
/*      */ 
/*      */ 
/*      */ 
/*      */ 
/*      */ 
/*      */ 
/*      */ 
/*      */ 
/*      */ 
/*      */ 
/*      */ 
/*      */ 
/*      */ 
/*      */ 
/*      */ 
/*      */ 
/*      */ 
/*      */ 
/*      */ 
/*      */ 
/*      */ 
/*      */ 
/*      */ 
/*      */ 
/*      */ 
/*      */ 
/*      */ 
/*      */ 
/*      */ 
/*      */ 
/*      */ 
/*      */ 
/*      */ 
/*      */ 
/*      */ 
/*      */ 
/*      */ 
/*      */ 
/*      */ 
/*      */ 
/*      */ 
/*      */ 
/*      */ 
/*      */ 
/*      */ 
/*      */ 
/*      */ 
/*      */ 
/*      */ 
/*      */ 
/*      */ 
/*      */ 
/*      */ 
/*      */ 
/*      */ 
/*      */ 
/*      */ 
/*      */ 
/*      */ 
/*      */ 
/*      */ 
/*      */ 
/*      */ 
/*      */ 
/*      */ 
/*      */ 
/*      */ 
/*      */ 
/*      */ 
/*      */ 
/*      */ 
/*      */ 
/*      */ 
/*      */ 
/*      */ 
/*      */ 
/*      */ 
/*      */ 
/*      */ 
/*      */ 
/*      */ 
/*      */ 
/*      */ 
/*      */ 
/*      */ 
/*      */ 
/*      */ 
/*      */ 
/*      */ 
/*      */ 
/*      */ 
/*      */ 
/*      */ 
/*      */ 
/*      */ 
/*      */ 
/*      */ 
/*      */ 
/*      */ 
/*      */ 
/*      */ 
/*      */ 
/*      */ 
/*      */ 
/*      */ 
/*      */ 
/*      */ 
/*      */ 
/*      */ 
/*      */ 
/*      */ 
/*      */ 
/*      */ 
/*      */ 
/*      */ 
/*      */ 
/*      */ 
/*      */ 
/*      */ 
/*      */ 
/*      */ 
/*      */ 
/*      */ 
/*      */ 
/*      */ 
/*      */ 
/*      */ 
/*      */ 
/*      */ 
/*      */ 
/*      */ 
/*      */ 
/*      */ 
/*      */ 
/*      */ 
/*      */ 
/*      */ 
/*      */ 
/*      */ 
/*      */ 
/*      */ 
/*      */ 
/*      */ 
/*      */ 
/*      */ 
/*      */ 
/*      */ 
/*      */ 
/*      */ 
/*      */ 
/*      */ 
/*      */ 
/*      */ 
/*      */ 
/*      */ 
/*      */ 
/*      */ 
/*      */ 
/*      */ 
/*      */ 
/*      */ 
/*      */ 
/*      */ 
/*      */ 
/*      */ 
/*      */ 
/*      */ 
/*      */ 
/*      */ 
/*      */ 
/*      */ 
/*      */ 
/*      */ 
/*      */ 
/*      */ 
/*      */ 
/*      */ 
/*      */ 
/*      */ 
/*      */ 
/*      */ 
/*      */ 
/*      */ 
/*      */ 
/*      */ 
/*      */ 
/*      */ 
/*      */ 
/*      */ 
/*      */ 
/*      */ 
/*      */ 
/*      */ 
/*      */ 
/*      */ 
/*      */ 
/*      */ 
/*      */ 
/*      */ 
/*      */ 
/*      */ 
/*      */ 
/*      */ 
/*      */ 
/*      */ 
/*      */ 
/*      */ 
/*      */ 
/*      */ 
/*      */ 
/*      */ 
/*      */ 
/*      */ 
/*      */ 
/*      */ 
/*      */ 
/*      */ 
/*      */ 
/*      */ 
/*      */ 
/*      */ 
/*      */ 
/*      */ 
/*      */ 
/*      */ 
/*      */ 
/*      */ 
/*      */ 
/*      */ 
/*      */ 
/*      */ 
/*      */ 
/*      */ 
/*      */ 
/*      */ 
/*      */ 
/*      */ 
/*      */ 
/*      */ 
/*      */ 
/*      */ 
/*      */ 
/*      */ 
/*      */ 
/*      */ 
/*      */ 
/*      */ 
/*      */ 
/*      */ 
/*      */ 
/*      */ 
/*      */ 
/*      */ 
/*      */ 
/*      */ 
/*      */ 
/*      */ 
/*      */ 
/*      */ 
/*      */ 
/*      */ 
/*      */ 
/*      */ 
/*      */ 
/*      */ 
/*      */ 
/*      */ 
/*      */ 
/*      */ 
/*      */ 
/*      */ 
/*      */ 
/*      */ 
/*      */ 
/*      */ 
/*      */ 
/*      */ 
/*      */ 
/*      */ 
/*      */ 
/*      */ 
/*      */ 
/*      */ 
/*      */ 
/*      */ 
/*      */ 
/*      */ 
/*      */ 
/*      */ 
/*      */ 
/*      */ 
/*      */ 
/*      */ 
/*      */ 
/*      */ 
/*      */ 
/*      */ 
/*      */ 
/*      */ 
/*      */ 
/*      */ 
/*      */ 
/*      */ 
/*      */ 
/*      */ 
/*      */ 
/*      */ 
/*      */ 
/*      */ 
/*      */ 
/*      */ 
/*      */ 
/*      */ 
/*      */ 
/*      */ 
/*      */ 
/*      */ 
/*      */ 
/*      */ 
/*      */ 
/*      */ 
/*      */ 
/*      */ 
/*      */ 
/*      */ 
/*      */ 
/*      */ 
/*      */ 
/*      */ 
/*      */ 
/*      */ 
/*      */ 
/*      */ 
/*      */ 
/*      */ 
/*      */ 
/*      */ 
/*      */ 
/*      */ 
/*      */ 
/*      */ 
/*      */ 
/*      */ 
/*      */ 
/*      */ 
/*      */ 
/*      */ 
/*      */ 
/*      */ 
/*      */ 
/*      */ 
/*      */ 
/*      */ 
/*      */ 
/*      */ 
/*      */ 
/*      */ 
/*      */ 
/*      */ 
/*      */ 
/*      */ 
/*      */ 
/*      */ 
/*      */ 
/*      */ 
/*      */ 
/*      */ 
/*      */ 
/*      */ 
/*      */ 
/*      */ 
/*      */ 
/*      */ 
/*      */ 
/*      */ 
/*      */ 
/*      */ 
/*      */ 
/*      */ 
/*      */ 
/*      */ 
/*      */ 
/*      */ 
/*      */ 
/*      */ 
/*      */ 
/*      */ 
/*      */ 
/*      */ 
/*      */ 
/*      */ 
/*      */ 
/*      */ 
/*      */ 
/*      */ 
/*      */ 
/*      */ 
/*      */ 
/*      */ 
/*      */ 
/*      */ 
/*      */ 
/*      */ 
/*      */ 
/*      */ 
/*      */ 
/*      */ 
/*      */ 
/*      */ 
/*      */ 
/*      */ 
/*      */ 
/*      */ 
/*      */ 
/*      */ 
/*      */ 
/*      */ 
/*      */ 
/*      */ 
/*      */ 
/*      */ 
/*      */ 
/*      */ 
/*      */ 
/*      */ 
/*      */ 
/*      */ 
/*      */ 
/*      */ 
/*      */ 
/*      */ 
/*      */ 
/*      */ 
/*      */ 
/*      */ 
/*      */ 
/*      */ 
/*      */ 
/*      */ 
/*      */ 
/*      */ 
/*      */ 
/*      */ 
/*      */ 
/*      */ 
/*      */ 
/*      */ 
/*      */ 
/*      */ 
/*      */ 
/*      */ 
/*      */ 
/*      */ 
/*      */ 
/*      */ 
/*      */ 
/*      */ 
/*      */ 
/*      */ 
/*      */ 
/*      */ 
/*      */ 
/*      */ 
/*      */ 
/*      */ 
/*      */ 
/*      */ 
/*      */ 
/*      */ 
/*      */ 
/*      */ 
/*      */ 
/*      */ 
/*      */ 
/*      */ 
/*      */ 
/*      */ 
/*      */ 
/*      */ 
/*      */ 
/*      */ 
/*      */ 
/*      */ 
/*      */ 
/*      */ 
/*      */ 
/*      */ 
/*      */ 
/*      */ 
/*      */ 
/*      */ 
/*      */ 
/*      */ 
/*      */ 
/*      */ 
/*      */ 
/*      */ 
/*      */ 
/*      */ 
/*      */ 
/*      */ 
/*      */ 
/*      */ 
/*      */ 
/*      */ 
/*      */ 
/*      */ 
/*      */ 
/*      */ 
/*      */ 
/*      */ 
/*      */ 
/*      */ 
/*      */ 
/*      */ 
/*      */ 
/*      */ 
/*      */ 
/*      */ 
/*      */ 
/*      */ 
/*      */ 
/*      */ 
/*      */ 
/*      */ 
/*      */ 
/*      */ 
/*      */ 
/*      */ 
/*      */ 
/*      */ 
/*      */ 
/*      */ 
/*      */ 
/*      */ 
/*      */ 
/*      */ 
/*      */ 
/*      */ 
/*      */ 
/*      */ 
/*      */ 
/*      */ 
/*      */ 
/*      */ 
/*      */ 
/*      */ 
/*      */ 
/*      */ 
/*      */ 
/*      */ 
/*      */ 
/*      */ 
/*      */ 
/*      */ 
/*      */ 
/*      */ 
/*      */ 
/*      */ 
/*      */ 
/*      */ 
/*      */ 
/*      */ 
/*      */ 
/*      */ 
/*      */ 
/*      */ 
/*      */ 
/*      */ 
/*      */ 
/*      */ 
/*      */ 
/*      */ 
/*      */ 
/*      */ 
/*      */ 
/*      */ 
/*      */ 
/*      */ 
/*      */ 
/*      */ 
/*      */ 
/*      */ 
/*      */ 
/*      */ 
/*      */ 
/*      */ 
/*      */ 
/*      */ 
/*      */ 
/*      */ 
/*      */ 
/*      */ 
/*      */ 
/*      */ 
/*      */ 
/*      */ 
/*      */ 
/*      */ 
/*      */ 
/*      */ 
/*      */ 
/*      */ 
/*      */ 
/*      */ 
/*      */ 
/*      */ 
/*      */ 
/*      */ 
/*      */ 
/*      */ 
/*      */ 
/*      */ 
/*      */ 
/*      */ 
/*      */ 
/*      */ 
/*      */ 
/*      */ 
/*      */ 
/*      */ 
/*      */ 
/*      */ 
/*      */ 
/*      */ 
/*      */ 
/*      */ 
/*      */ 
/*      */ 
/*      */ 
/*      */ 
/*      */ 
/*      */ 
/*      */ 
/*      */ 
/*      */ 
/*      */ 
/*      */ 
/*      */ 
/*      */ 
/*      */ 
/*      */ 
/*      */ 
/*      */ 
/*      */ 
/*      */ 
/*      */ 
/*      */ 
/*      */ 
/*      */ 
/*      */ 
/*      */ 
/*      */ 
/*      */ 
/*      */ 
/*      */ 
/*      */ 
/*      */ 
/*      */ 
/*      */ 
/*      */ 
/*      */ 
/*      */ 
/*      */ 
/*      */ 
/*      */ 
/*      */ 
/*      */ 
/*      */ 
/*      */ 
/*      */ 
/*      */ 
/*      */ 
/*      */ 
/*      */ 
/*      */ 
/*      */ 
/*      */ 
/*      */ 
/*      */ 
/*      */ 
/*      */ 
/*      */ 
/*      */ 
/*      */ 
/*      */ 
/*      */ 
/*      */ 
/*      */ 
/*      */ 
/*      */ 
/*      */ 
/*      */ 
/*      */ 
/*      */ 
/*      */ 
/*      */ 
/*      */ 
/*      */ 
/*      */ 
/*      */ 
/*      */ 
/*      */ 
/*      */ 
/*      */ 
/*      */ 
/*      */ 
/*      */ 
/*      */ 
/*      */ 
/*      */ 
/*      */ 
/*      */ 
/*      */ 
/*      */ 
/*      */ 
/*      */ 
/*      */ 
/*      */ 
/*      */ 
/*      */ 
/*      */ 
/*      */ 
/*      */ 
/*      */ 
/*      */ 
/*      */ 
/*      */ 
/*      */ 
/*      */ 
/*      */ 
/*      */ 
/*      */ 
/*      */ 
/*      */ 
/*      */ 
/*      */ 
/*      */ 
/*      */ 
/*      */ 
/*      */ 
/*      */ 
/*      */ 
/*      */ 
/*      */ 
/*      */ 
/*      */ 
/*      */ 
/*      */ 
/*      */ 
/*      */ 
/*      */ 
/*      */ 
/*      */ 
/*      */ 
/*      */ 
/*      */ 
/*      */ 
/*      */ 
/*      */ 
/*      */ 
/*      */ 
/*      */ 
/*      */ 
/*      */ 
/*      */ 
/*      */ 
/*      */ 
/*      */ 
/*      */ 
/*      */ 
/*      */ 
/*      */ 
/*      */ 
/*      */ 
/*      */ 
/*      */ 
/*      */ 
/*      */ 
/*      */ 
/*      */ 
/*      */ 
/*      */ 
/*      */ 
/*      */ 
/*      */ 
/*      */ 
/*      */ 
/*      */ 
/*      */ 
/*      */ 
/*      */ 
/*      */ 
/*      */ 
/*      */ 
/*      */ 
/*      */ 
/*      */ 
/*      */ 
/*      */ 
/*      */ 
/*      */ 
/*      */ 
/*      */ 
/*      */ 
/*      */ 
/*      */ 
/*      */ 
/*      */ 
/*      */ 
/*      */ 
/*      */ 
/*      */ 
/*      */ 
/*      */ 
/*      */ 
/*      */ 
/*      */ 
/*      */ 
/*      */ 
/*      */ 
/*      */ 
/*      */ 
/*      */ 
/*      */ 
/*      */ 
/*      */ 
/*      */ 
/*      */ 
/*      */ 
/*      */ 
/*      */ 
/*      */ 
/*      */ 
/*      */ 
/*      */ 
/*      */ 
/*      */ 
/*      */ 
/*      */ 
/*      */ 
/*      */ 
/*      */ 
/*      */ 
/*      */ 
/*      */ 
/*      */ 
/*      */ 
/*      */ 
/*      */ 
/*      */ 
/*      */ 
/*      */ 
/*      */ 
/*      */ 
/*      */ 
/*      */ 
/*      */ 
/*      */ 
/*      */ 
/*      */ 
/*      */ 
/*      */ 
/*      */ 
/*      */ 
/*      */ 
/*      */ 
/*      */ 
/*      */ 
/*      */ 
/*      */ 
/*      */ 
/*      */ 
/*      */ 
/*      */ 
/*      */ 
/*      */ 
/*      */ 
/*      */ 
/*      */ 
/*      */ class ReuseableEvents
/*      */ {
/*      */   public static final AnimationEvent.E0 FAST_SPINNING;
/*      */   public static final AnimationEvent.E0 TRIDENT_SPINNING;
/*      */   public static final AnimationEvent.E0 PLAY_TRIDENT_EFFECT_HAND_LEFT;
/*      */   public static final AnimationEvent.E0 PLAY_TRIDENT_EFFECT_WEAPON_RIGHT;
/*      */   public static final AnimationEvent.E0 PLAY_TRIDENT_EFFECT_HAND_RIGHT;
/*      */   public static final AnimationEvent.E0 THROW_TRIDENT_HAND_LEFT;
/*      */   public static final AnimationEvent.E0 THROW_TRIDENT_HAND_RIGHT;
/*      */   public static final AnimationEvent.E0 THROW_TRIDENT_HAND_LEFT_LIGHTNING;
/*      */   public static final AnimationEvent.E0 THROW_TRIDENT_HAND_RIGHT_LIGHTNING;
/*      */   public static final AnimationEvent.E0 THROW_TRIDENT_HAND_RIGHT_EXPLODE;
/*      */   public static final AnimationEvent.E0 SUMMON_2_OBSIDIAN_LEG_RIGHT;
/*      */   public static final AnimationEvent.E0 SUMMON_2_OBSIDIAN_LEG_LEFT;
/*      */   public static final AnimationEvent.E0 SUMMON_2_OBSIDIAN_HAND_RIGHT;
/*      */   public static final AnimationEvent.E0 SUMMON_2_OBSIDIAN_HAND_LEFT;
/*      */   public static final AnimationEvent.E0 SUMMON_3_OBSIDIAN_HAND_LEFT;
/*      */   public static final AnimationEvent.E0 SUMMON_6_OBSIDIAN_HAND_LEFT;
/*      */   public static final AnimationEvent.E0 SUMMON_6_OBSIDIAN_HAND_RIGHT;
/*      */   public static final AnimationEvent.E0 SUMMON_6_OBSIDIAN_LEG_RIGHT;
/*      */   public static final AnimationEvent.E0 SUMMON_OBSIDIAN_PILLAR;
/*      */   public static final AnimationEvent.E0 SUMMON_OBSIDIAN_WALL;
/*      */   public static final AnimationEvent.E0 SUMMON_OBSIDIAN_CIRCLE;
/*      */   public static final AnimationEvent.E0 SUMMON_OBSIDIAN_CROSS;
/*      */   public static final AnimationEvent.E0 SUMMON_OBSIDIAN_CROSS_FIX_DELAY_SHADOW_HEROBRINE;
/*      */   public static final AnimationEvent.E0 SUMMON_OBSIDIAN_SMALL_CROSS;
/*      */   public static final AnimationEvent.E0 THROW_OBSIDIAN;
/*      */   public static final AnimationEvent.E0 THROW_OBSIDIAN_OFFHAND;
/*      */   
/*      */   static {
/* 3581 */     FAST_SPINNING = ((livingentitypatch, staticAnimation, aobject) -> ((LivingEntity)livingentitypatch.getOriginal()).m_9236_().m_6269_((Player)livingentitypatch.getOriginal(), livingentitypatch.getOriginal(), (SoundEvent)EpicFightSounds.WHOOSH.get(), SoundSource.NEUTRAL, 0.5F, 1.1F - ((new Random()).nextFloat() - 0.5F) * 0.2F));
/*      */     
/* 3583 */     TRIDENT_SPINNING = ((livingentitypatch, staticAnimation, aobject) -> ((LivingEntity)livingentitypatch.getOriginal()).m_9236_().m_6269_((Player)livingentitypatch.getOriginal(), livingentitypatch.getOriginal(), SoundEvents.f_12516_, SoundSource.NEUTRAL, 0.5F, 1.1F - ((new Random()).nextFloat() - 0.5F) * 0.2F));
/*      */     
/* 3585 */     PLAY_TRIDENT_EFFECT_HAND_LEFT = ((livingEntityPatch, staticAnimation, object) -> {
/*      */         LivingEntity livingEntity = (LivingEntity)livingEntityPatch.getOriginal();
/*      */ 
/*      */         
/*      */         Level patt348823$temp = livingEntity.m_9236_();
/*      */ 
/*      */         
/*      */         if (patt348823$temp instanceof ServerLevel) {
/*      */           ServerLevel serverLevel = (ServerLevel)patt348823$temp;
/*      */ 
/*      */           
/*      */           Item weapon = livingEntity.m_21205_().m_41720_();
/*      */ 
/*      */           
/*      */           if (weapon instanceof BlueDemonTridentItem) {
/*      */             Vec3 jointVec = EpicfightUtil.getJointWithTranslation((Entity)livingEntity, new Vec3f(0.0F, 0.0F, 0.0F), ((HumanoidArmature)Armatures.BIPED.get()).handL, (new Random()).nextFloat(-1.0F, 1.0F), 0.0D);
/*      */ 
/*      */             
/*      */             if (jointVec == null) {
/*      */               return;
/*      */             }
/*      */ 
/*      */             
/*      */             serverLevel.m_8767_((ParticleOptions)AnnoyingVillagersModParticleTypes.ELECTRIC_SPARK.get(), jointVec.f_82479_, jointVec.f_82480_, jointVec.f_82481_, 1, 0.0D, 0.0D, 0.0D, 0.0D);
/*      */             
/*      */             float volume = (float)Mth.m_216263_(serverLevel.f_46441_, 0.05D, 0.5D);
/*      */             
/*      */             float pitch = (float)Mth.m_216263_(serverLevel.f_46441_, 0.8D, 1.1D);
/*      */             
/*      */             serverLevel.m_5594_(null, BlockPos.m_274561_(jointVec.f_82479_, jointVec.f_82480_, jointVec.f_82481_), (SoundEvent)AnnoyingVillagersModSounds.ELECTRIFY.get(), SoundSource.NEUTRAL, volume, pitch);
/*      */           } 
/*      */         } 
/*      */       });
/*      */     
/* 3619 */     PLAY_TRIDENT_EFFECT_WEAPON_RIGHT = ((livingEntityPatch, staticAnimation, object) -> {
/*      */         LivingEntity livingEntity = (LivingEntity)livingEntityPatch.getOriginal();
/*      */ 
/*      */         
/*      */         Level patt350759$temp = livingEntity.m_9236_();
/*      */ 
/*      */         
/*      */         if (patt350759$temp instanceof ServerLevel) {
/*      */           ServerLevel serverLevel = (ServerLevel)patt350759$temp;
/*      */ 
/*      */           
/*      */           Item weapon = livingEntity.m_21205_().m_41720_();
/*      */ 
/*      */           
/*      */           if (weapon instanceof BlueDemonTridentItem) {
/*      */             Vec3 jointVec = EpicfightUtil.getJointWithTranslation((Entity)livingEntity, new Vec3f(0.0F, 0.0F, 0.0F), ((HumanoidArmature)Armatures.BIPED.get()).toolR, (new Random()).nextFloat(-1.0F, 1.0F), 0.0D);
/*      */ 
/*      */             
/*      */             if (jointVec == null) {
/*      */               return;
/*      */             }
/*      */ 
/*      */             
/*      */             serverLevel.m_8767_((ParticleOptions)AnnoyingVillagersModParticleTypes.ELECTRIC_SPARK.get(), jointVec.f_82479_, jointVec.f_82480_, jointVec.f_82481_, 1, 0.0D, 0.0D, 0.0D, 0.0D);
/*      */             
/*      */             float volume = (float)Mth.m_216263_(serverLevel.f_46441_, 0.05D, 0.5D);
/*      */             
/*      */             float pitch = (float)Mth.m_216263_(serverLevel.f_46441_, 0.8D, 1.1D);
/*      */             
/*      */             serverLevel.m_5594_(null, BlockPos.m_274561_(jointVec.f_82479_, jointVec.f_82480_, jointVec.f_82481_), (SoundEvent)AnnoyingVillagersModSounds.ELECTRIFY.get(), SoundSource.NEUTRAL, volume, pitch);
/*      */           } 
/*      */         } 
/*      */       });
/*      */     
/* 3653 */     PLAY_TRIDENT_EFFECT_HAND_RIGHT = ((livingEntityPatch, staticAnimation, object) -> {
/*      */         LivingEntity livingEntity = (LivingEntity)livingEntityPatch.getOriginal();
/*      */ 
/*      */         
/*      */         Level patt352693$temp = livingEntity.m_9236_();
/*      */ 
/*      */         
/*      */         if (patt352693$temp instanceof ServerLevel) {
/*      */           ServerLevel serverLevel = (ServerLevel)patt352693$temp;
/*      */ 
/*      */           
/*      */           Item weapon = livingEntity.m_21205_().m_41720_();
/*      */ 
/*      */           
/*      */           if (weapon instanceof BlueDemonTridentItem) {
/*      */             Vec3 jointVec = EpicfightUtil.getJointWithTranslation((Entity)livingEntity, new Vec3f(0.0F, 0.0F, 0.0F), ((HumanoidArmature)Armatures.BIPED.get()).handR, (new Random()).nextFloat(-1.0F, 1.0F), 0.0D);
/*      */ 
/*      */             
/*      */             if (jointVec == null) {
/*      */               return;
/*      */             }
/*      */ 
/*      */             
/*      */             serverLevel.m_8767_((ParticleOptions)AnnoyingVillagersModParticleTypes.ELECTRIC_SPARK.get(), jointVec.f_82479_, jointVec.f_82480_, jointVec.f_82481_, 1, 0.0D, 0.0D, 0.0D, 0.0D);
/*      */             
/*      */             float volume = (float)Mth.m_216263_(serverLevel.f_46441_, 0.05D, 0.5D);
/*      */             
/*      */             float pitch = (float)Mth.m_216263_(serverLevel.f_46441_, 0.8D, 1.1D);
/*      */             
/*      */             serverLevel.m_5594_(null, BlockPos.m_274561_(jointVec.f_82479_, jointVec.f_82480_, jointVec.f_82481_), (SoundEvent)AnnoyingVillagersModSounds.ELECTRIFY.get(), SoundSource.NEUTRAL, volume, pitch);
/*      */           } 
/*      */         } 
/*      */       });
/*      */     
/* 3687 */     THROW_TRIDENT_HAND_LEFT = ((livingEntityPatch, staticAnimation, object) -> {
/*      */         LivingEntity livingEntity = (LivingEntity)livingEntityPatch.getOriginal();
/*      */         
/*      */         Level patt354620$temp = livingEntity.m_9236_();
/*      */         if (patt354620$temp instanceof ServerLevel) {
/*      */           ServerLevel serverLevel = (ServerLevel)patt354620$temp;
/*      */           ItemStack stack = livingEntity.m_21206_();
/*      */           Item weapon = stack.m_41720_();
/*      */           if (weapon instanceof BlueDemonTridentItem) {
/*      */             if (livingEntity instanceof Player) {
/*      */               Player player = (Player)livingEntity;
/*      */               stack.m_41622_(1, (LivingEntity)player, ());
/*      */             } 
/*      */             Vec3 jointVec = EpicfightUtil.getJointWithTranslation((Entity)livingEntity, new Vec3f(0.0F, 0.0F, 0.0F), ((HumanoidArmature)Armatures.BIPED.get()).handL, 0.0F, 0.0D);
/*      */             if (jointVec == null) {
/*      */               return;
/*      */             }
/*      */             Vec3 direction = BlueDemonTridentItem.getTridentThrowDirection(livingEntity, jointVec);
/*      */             if (direction == null || direction.m_82556_() < 1.0E-7D) {
/*      */               return;
/*      */             }
/*      */             BlueDemonThrownTridentEntity trident = new BlueDemonThrownTridentEntity((Level)serverLevel, livingEntity, stack.m_41777_());
/*      */             trident.assignSpawnSequence(livingEntity);
/*      */             trident.trimOldGroundedTridentsAroundOwnerOnSpawn();
/*      */             trident.m_6034_(jointVec.f_82479_, jointVec.f_82480_, jointVec.f_82481_);
/*      */             trident.m_146922_((float)(Mth.m_14136_(direction.f_82479_, direction.f_82481_) * 57.29577951308232D));
/*      */             trident.m_146926_((float)(Mth.m_14136_(direction.f_82480_, Math.sqrt(direction.f_82479_ * direction.f_82479_ + direction.f_82481_ * direction.f_82481_)) * 57.29577951308232D));
/*      */             float speed = 2.5F;
/*      */             float inaccuracy = 1.0F;
/*      */             trident.f_36705_ = AbstractArrow.Pickup.DISALLOWED;
/*      */             trident.m_6686_(direction.f_82479_, direction.f_82480_, direction.f_82481_, speed, inaccuracy);
/*      */             serverLevel.m_7967_((Entity)trident);
/*      */           } 
/*      */         } 
/*      */       });
/* 3722 */     THROW_TRIDENT_HAND_RIGHT = ((livingEntityPatch, staticAnimation, object) -> {
/*      */         LivingEntity livingEntity = (LivingEntity)livingEntityPatch.getOriginal();
/*      */         
/*      */         Level patt356969$temp = livingEntity.m_9236_();
/*      */         if (patt356969$temp instanceof ServerLevel) {
/*      */           ServerLevel serverLevel = (ServerLevel)patt356969$temp;
/*      */           ItemStack stack = livingEntity.m_21205_();
/*      */           Item weapon = stack.m_41720_();
/*      */           if (weapon instanceof BlueDemonTridentItem) {
/*      */             if (livingEntity instanceof Player) {
/*      */               Player player = (Player)livingEntity;
/*      */               stack.m_41622_(1, (LivingEntity)player, ());
/*      */             } 
/*      */             Vec3 jointVec = EpicfightUtil.getJointWithTranslation((Entity)livingEntity, new Vec3f(0.0F, 0.0F, 0.0F), ((HumanoidArmature)Armatures.BIPED.get()).handR, 0.0F, 0.0D);
/*      */             if (jointVec == null) {
/*      */               return;
/*      */             }
/*      */             Vec3 direction = BlueDemonTridentItem.getTridentThrowDirection(livingEntity, jointVec);
/*      */             if (direction == null || direction.m_82556_() < 1.0E-7D) {
/*      */               return;
/*      */             }
/*      */             BlueDemonThrownTridentEntity trident = new BlueDemonThrownTridentEntity((Level)serverLevel, livingEntity, stack.m_41777_());
/*      */             trident.assignSpawnSequence(livingEntity);
/*      */             trident.trimOldGroundedTridentsAroundOwnerOnSpawn();
/*      */             trident.m_6034_(jointVec.f_82479_, jointVec.f_82480_, jointVec.f_82481_);
/*      */             trident.m_146922_((float)(Mth.m_14136_(direction.f_82479_, direction.f_82481_) * 57.29577951308232D));
/*      */             trident.m_146926_((float)(Mth.m_14136_(direction.f_82480_, Math.sqrt(direction.f_82479_ * direction.f_82479_ + direction.f_82481_ * direction.f_82481_)) * 57.29577951308232D));
/*      */             float speed = 2.5F;
/*      */             float inaccuracy = 1.0F;
/*      */             trident.f_36705_ = AbstractArrow.Pickup.DISALLOWED;
/*      */             trident.m_6686_(direction.f_82479_, direction.f_82480_, direction.f_82481_, speed, inaccuracy);
/*      */             serverLevel.m_7967_((Entity)trident);
/*      */           } 
/*      */         } 
/*      */       });
/* 3757 */     THROW_TRIDENT_HAND_LEFT_LIGHTNING = ((livingEntityPatch, staticAnimation, object) -> {
/*      */         LivingEntity livingEntity = (LivingEntity)livingEntityPatch.getOriginal();
/*      */         
/*      */         Level patt359328$temp = livingEntity.m_9236_();
/*      */         if (patt359328$temp instanceof ServerLevel) {
/*      */           ServerLevel serverLevel = (ServerLevel)patt359328$temp;
/*      */           ItemStack stack = livingEntity.m_21206_();
/*      */           Item weapon = stack.m_41720_();
/*      */           if (weapon instanceof BlueDemonTridentItem) {
/*      */             if (livingEntity instanceof Player) {
/*      */               Player player = (Player)livingEntity;
/*      */               stack.m_41622_(1, (LivingEntity)player, ());
/*      */             } 
/*      */             Vec3 jointVec = EpicfightUtil.getJointWithTranslation((Entity)livingEntity, new Vec3f(0.0F, 0.0F, 0.0F), ((HumanoidArmature)Armatures.BIPED.get()).handL, 0.0F, 0.0D);
/*      */             if (jointVec == null) {
/*      */               return;
/*      */             }
/*      */             Vec3 direction = BlueDemonTridentItem.getTridentThrowDirection(livingEntity, jointVec);
/*      */             if (direction == null || direction.m_82556_() < 1.0E-7D) {
/*      */               return;
/*      */             }
/*      */             BlueDemonThrownTridentEntity trident = new BlueDemonThrownTridentEntity((Level)serverLevel, livingEntity, stack.m_41777_());
/*      */             trident.assignSpawnSequence(livingEntity);
/*      */             trident.trimOldGroundedTridentsAroundOwnerOnSpawn();
/*      */             trident.setMode(TridentMode.LIGHTNING);
/*      */             trident.m_6034_(jointVec.f_82479_, jointVec.f_82480_, jointVec.f_82481_);
/*      */             trident.m_146922_((float)(Mth.m_14136_(direction.f_82479_, direction.f_82481_) * 57.29577951308232D));
/*      */             trident.m_146926_((float)(Mth.m_14136_(direction.f_82480_, Math.sqrt(direction.f_82479_ * direction.f_82479_ + direction.f_82481_ * direction.f_82481_)) * 57.29577951308232D));
/*      */             float speed = 2.5F;
/*      */             float inaccuracy = 1.0F;
/*      */             trident.f_36705_ = AbstractArrow.Pickup.DISALLOWED;
/*      */             trident.m_6686_(direction.f_82479_, direction.f_82480_, direction.f_82481_, speed, inaccuracy);
/*      */             serverLevel.m_7967_((Entity)trident);
/*      */           } 
/*      */         } 
/*      */       });
/* 3793 */     THROW_TRIDENT_HAND_RIGHT_LIGHTNING = ((livingEntityPatch, staticAnimation, object) -> {
/*      */         LivingEntity livingEntity = (LivingEntity)livingEntityPatch.getOriginal();
/*      */         
/*      */         Level patt361756$temp = livingEntity.m_9236_();
/*      */         if (patt361756$temp instanceof ServerLevel) {
/*      */           ServerLevel serverLevel = (ServerLevel)patt361756$temp;
/*      */           ItemStack stack = livingEntity.m_21205_();
/*      */           Item weapon = stack.m_41720_();
/*      */           if (weapon instanceof BlueDemonTridentItem) {
/*      */             if (livingEntity instanceof Player) {
/*      */               Player player = (Player)livingEntity;
/*      */               stack.m_41622_(1, (LivingEntity)player, ());
/*      */             } 
/*      */             Vec3 jointVec = EpicfightUtil.getJointWithTranslation((Entity)livingEntity, new Vec3f(0.0F, 0.0F, 0.0F), ((HumanoidArmature)Armatures.BIPED.get()).handR, 0.0F, 0.0D);
/*      */             if (jointVec == null) {
/*      */               return;
/*      */             }
/*      */             Vec3 direction = BlueDemonTridentItem.getTridentThrowDirection(livingEntity, jointVec);
/*      */             if (direction == null || direction.m_82556_() < 1.0E-7D) {
/*      */               return;
/*      */             }
/*      */             BlueDemonThrownTridentEntity trident = new BlueDemonThrownTridentEntity((Level)serverLevel, livingEntity, stack.m_41777_());
/*      */             trident.assignSpawnSequence(livingEntity);
/*      */             trident.trimOldGroundedTridentsAroundOwnerOnSpawn();
/*      */             trident.setMode(TridentMode.LIGHTNING);
/*      */             trident.m_6034_(jointVec.f_82479_, jointVec.f_82480_, jointVec.f_82481_);
/*      */             trident.m_146922_((float)(Mth.m_14136_(direction.f_82479_, direction.f_82481_) * 57.29577951308232D));
/*      */             trident.m_146926_((float)(Mth.m_14136_(direction.f_82480_, Math.sqrt(direction.f_82479_ * direction.f_82479_ + direction.f_82481_ * direction.f_82481_)) * 57.29577951308232D));
/*      */             float speed = 2.5F;
/*      */             float inaccuracy = 1.0F;
/*      */             trident.f_36705_ = AbstractArrow.Pickup.DISALLOWED;
/*      */             trident.m_6686_(direction.f_82479_, direction.f_82480_, direction.f_82481_, speed, inaccuracy);
/*      */             serverLevel.m_7967_((Entity)trident);
/*      */           } 
/*      */         } 
/*      */       });
/* 3829 */     THROW_TRIDENT_HAND_RIGHT_EXPLODE = ((livingEntityPatch, staticAnimation, object) -> {
/*      */         LivingEntity livingEntity = (LivingEntity)livingEntityPatch.getOriginal();
/*      */         
/*      */         Level patt364183$temp = livingEntity.m_9236_();
/*      */         if (patt364183$temp instanceof ServerLevel) {
/*      */           ServerLevel serverLevel = (ServerLevel)patt364183$temp;
/*      */           ItemStack stack = livingEntity.m_21205_();
/*      */           Item weapon = stack.m_41720_();
/*      */           if (weapon instanceof BlueDemonTridentItem) {
/*      */             if (livingEntity instanceof Player) {
/*      */               Player player = (Player)livingEntity;
/*      */               stack.m_41622_(1, (LivingEntity)player, ());
/*      */             } 
/*      */             Vec3 jointVec = EpicfightUtil.getJointWithTranslation((Entity)livingEntity, new Vec3f(0.0F, 0.0F, 0.0F), ((HumanoidArmature)Armatures.BIPED.get()).handR, 0.0F, 0.0D);
/*      */             if (jointVec == null) {
/*      */               return;
/*      */             }
/*      */             Vec3 direction = BlueDemonTridentItem.getTridentThrowDirection(livingEntity, jointVec);
/*      */             if (direction == null || direction.m_82556_() < 1.0E-7D) {
/*      */               return;
/*      */             }
/*      */             BlueDemonThrownTridentEntity trident = new BlueDemonThrownTridentEntity((Level)serverLevel, livingEntity, stack.m_41777_());
/*      */             trident.assignSpawnSequence(livingEntity);
/*      */             trident.trimOldGroundedTridentsAroundOwnerOnSpawn();
/*      */             trident.setMode(TridentMode.EXPLOSION);
/*      */             trident.m_6034_(jointVec.f_82479_, jointVec.f_82480_, jointVec.f_82481_);
/*      */             trident.m_146922_((float)(Mth.m_14136_(direction.f_82479_, direction.f_82481_) * 57.29577951308232D));
/*      */             trident.m_146926_((float)(Mth.m_14136_(direction.f_82480_, Math.sqrt(direction.f_82479_ * direction.f_82479_ + direction.f_82481_ * direction.f_82481_)) * 57.29577951308232D));
/*      */             float speed = 2.5F;
/*      */             float inaccuracy = 1.0F;
/*      */             trident.f_36705_ = AbstractArrow.Pickup.DISALLOWED;
/*      */             trident.m_6686_(direction.f_82479_, direction.f_82480_, direction.f_82481_, speed, inaccuracy);
/*      */             serverLevel.m_7967_((Entity)trident);
/*      */           } 
/*      */         } 
/*      */       });
/* 3865 */     SUMMON_2_OBSIDIAN_LEG_RIGHT = ((livingEntityPatch, staticAnimation, object) -> {
/*      */         LivingEntity livingEntity = (LivingEntity)livingEntityPatch.getOriginal();
/*      */         
/*      */         Level patt366605$temp = livingEntity.m_9236_();
/*      */         
/*      */         if (patt366605$temp instanceof ServerLevel) {
/*      */           ServerLevel serverLevel = (ServerLevel)patt366605$temp;
/*      */           
/*      */           Item weapon = livingEntity.m_21205_().m_41720_();
/*      */           if (weapon instanceof com.pla.annoyingvillagers.item.ShadowObsidianWeaponItem || weapon instanceof com.pla.annoyingvillagers.item.ObsidianWeaponItem) {
/*      */             BlockState obsidian;
/*      */             if (weapon instanceof com.pla.annoyingvillagers.item.ShadowObsidianWeaponItem) {
/*      */               obsidian = (BlockState)((Block)AnnoyingVillagersModBlocks.SHADOW_OBSIDIAN_BLOCK.get()).m_49966_().m_61124_((Property)ShadowObsidianBlock.FROM_PLAYER, Boolean.valueOf(livingEntity instanceof Player));
/*      */             } else {
/*      */               obsidian = (BlockState)((Block)AnnoyingVillagersModBlocks.OBSIDIAN_BLOCK.get()).m_49966_().m_61124_((Property)ObsidianBlock.FROM_PLAYER, Boolean.valueOf(livingEntity instanceof Player));
/*      */             } 
/*      */             HerobrineUtil.summonObsidianBlocksInfrontOf(serverLevel, livingEntity, obsidian, 2, ((HumanoidArmature)Armatures.BIPED.get()).legR);
/*      */           } else if (weapon instanceof com.pla.annoyingvillagers.item.ShadowObsidianPillarItem) {
/*      */             HerobrineUtil.summonShadowObsidianShortPillarShootToward(serverLevel, (Entity)livingEntity, 3, ((HumanoidArmature)Armatures.BIPED.get()).legR);
/*      */           } 
/*      */         } 
/*      */       });
/* 3887 */     SUMMON_2_OBSIDIAN_LEG_LEFT = ((livingEntityPatch, staticAnimation, object) -> {
/*      */         LivingEntity livingEntity = (LivingEntity)livingEntityPatch.getOriginal();
/*      */         
/*      */         Level patt368290$temp = livingEntity.m_9236_();
/*      */         
/*      */         if (patt368290$temp instanceof ServerLevel) {
/*      */           ServerLevel serverLevel = (ServerLevel)patt368290$temp;
/*      */           
/*      */           Item weapon = livingEntity.m_21205_().m_41720_();
/*      */           if (weapon instanceof com.pla.annoyingvillagers.item.ShadowObsidianWeaponItem || weapon instanceof com.pla.annoyingvillagers.item.ObsidianWeaponItem) {
/*      */             BlockState obsidian;
/*      */             if (weapon instanceof com.pla.annoyingvillagers.item.ShadowObsidianWeaponItem) {
/*      */               obsidian = (BlockState)((Block)AnnoyingVillagersModBlocks.SHADOW_OBSIDIAN_BLOCK.get()).m_49966_().m_61124_((Property)ShadowObsidianBlock.FROM_PLAYER, Boolean.valueOf(livingEntity instanceof Player));
/*      */             } else {
/*      */               obsidian = (BlockState)((Block)AnnoyingVillagersModBlocks.OBSIDIAN_BLOCK.get()).m_49966_().m_61124_((Property)ObsidianBlock.FROM_PLAYER, Boolean.valueOf(livingEntity instanceof Player));
/*      */             } 
/*      */             HerobrineUtil.summonObsidianBlocksInfrontOf(serverLevel, livingEntity, obsidian, 2, ((HumanoidArmature)Armatures.BIPED.get()).legL);
/*      */           } else if (weapon instanceof com.pla.annoyingvillagers.item.ShadowObsidianPillarItem) {
/*      */             HerobrineUtil.summonShadowObsidianShortPillarShootToward(serverLevel, (Entity)livingEntity, 3, ((HumanoidArmature)Armatures.BIPED.get()).legL);
/*      */           } 
/*      */         } 
/*      */       });
/* 3909 */     SUMMON_2_OBSIDIAN_HAND_RIGHT = ((livingEntityPatch, staticAnimation, object) -> {
/*      */         LivingEntity livingEntity = (LivingEntity)livingEntityPatch.getOriginal();
/*      */         
/*      */         Level patt369977$temp = livingEntity.m_9236_();
/*      */         
/*      */         if (patt369977$temp instanceof ServerLevel) {
/*      */           ServerLevel serverLevel = (ServerLevel)patt369977$temp;
/*      */           
/*      */           Item weapon = livingEntity.m_21205_().m_41720_();
/*      */           if (weapon instanceof com.pla.annoyingvillagers.item.ShadowObsidianWeaponItem || weapon instanceof com.pla.annoyingvillagers.item.ObsidianWeaponItem) {
/*      */             BlockState obsidian;
/*      */             if (weapon instanceof com.pla.annoyingvillagers.item.ShadowObsidianWeaponItem) {
/*      */               obsidian = (BlockState)((Block)AnnoyingVillagersModBlocks.SHADOW_OBSIDIAN_BLOCK.get()).m_49966_().m_61124_((Property)ShadowObsidianBlock.FROM_PLAYER, Boolean.valueOf(livingEntity instanceof Player));
/*      */             } else {
/*      */               obsidian = (BlockState)((Block)AnnoyingVillagersModBlocks.OBSIDIAN_BLOCK.get()).m_49966_().m_61124_((Property)ObsidianBlock.FROM_PLAYER, Boolean.valueOf(livingEntity instanceof Player));
/*      */             } 
/*      */             HerobrineUtil.summonObsidianBlocksInfrontOf(serverLevel, livingEntity, obsidian, 2, ((HumanoidArmature)Armatures.BIPED.get()).toolR);
/*      */           } else if (weapon instanceof com.pla.annoyingvillagers.item.ShadowObsidianPillarItem) {
/*      */             HerobrineUtil.summonShadowObsidianShortPillarShootToward(serverLevel, (Entity)livingEntity, 3, ((HumanoidArmature)Armatures.BIPED.get()).toolR);
/*      */           } else if (livingEntity.m_21206_().m_41720_() instanceof com.pla.annoyingvillagers.item.ShadowObsidianSwordItem) {
/*      */             HerobrineUtil.summonShadowObsidianMiddlePillarShootToward(serverLevel, (Entity)livingEntity, 3, ((HumanoidArmature)Armatures.BIPED.get()).toolR);
/*      */           } 
/*      */         } 
/*      */       });
/* 3933 */     SUMMON_2_OBSIDIAN_HAND_LEFT = ((livingEntityPatch, staticAnimation, object) -> {
/*      */         LivingEntity livingEntity = (LivingEntity)livingEntityPatch.getOriginal();
/*      */         
/*      */         Level patt371926$temp = livingEntity.m_9236_();
/*      */         
/*      */         if (patt371926$temp instanceof ServerLevel) {
/*      */           ServerLevel serverLevel = (ServerLevel)patt371926$temp;
/*      */           
/*      */           Item weapon = livingEntity.m_21205_().m_41720_();
/*      */           if (weapon instanceof com.pla.annoyingvillagers.item.ShadowObsidianWeaponItem || weapon instanceof com.pla.annoyingvillagers.item.ObsidianWeaponItem) {
/*      */             BlockState obsidian;
/*      */             if (weapon instanceof com.pla.annoyingvillagers.item.ShadowObsidianWeaponItem) {
/*      */               obsidian = (BlockState)((Block)AnnoyingVillagersModBlocks.SHADOW_OBSIDIAN_BLOCK.get()).m_49966_().m_61124_((Property)ShadowObsidianBlock.FROM_PLAYER, Boolean.valueOf(livingEntity instanceof Player));
/*      */             } else {
/*      */               obsidian = (BlockState)((Block)AnnoyingVillagersModBlocks.OBSIDIAN_BLOCK.get()).m_49966_().m_61124_((Property)ObsidianBlock.FROM_PLAYER, Boolean.valueOf(livingEntity instanceof Player));
/*      */             } 
/*      */             HerobrineUtil.summonObsidianBlocksInfrontOf(serverLevel, livingEntity, obsidian, 2, ((HumanoidArmature)Armatures.BIPED.get()).toolL);
/*      */           } else if (livingEntity.m_21206_().m_41720_() instanceof com.pla.annoyingvillagers.item.ShadowObsidianSwordItem) {
/*      */             HerobrineUtil.summonShadowObsidianMiddlePillarShootToward(serverLevel, (Entity)livingEntity, 3, ((HumanoidArmature)Armatures.BIPED.get()).toolL);
/*      */           } else if (weapon instanceof com.pla.annoyingvillagers.item.ShadowObsidianPillarItem) {
/*      */             HerobrineUtil.summonShadowObsidianShortPillarShootToward(serverLevel, (Entity)livingEntity, 3, ((HumanoidArmature)Armatures.BIPED.get()).toolL);
/*      */           } 
/*      */         } 
/*      */       });
/* 3957 */     SUMMON_3_OBSIDIAN_HAND_LEFT = ((livingEntityPatch, staticAnimation, object) -> {
/*      */         LivingEntity livingEntity = (LivingEntity)livingEntityPatch.getOriginal();
/*      */         
/*      */         Level patt373875$temp = livingEntity.m_9236_();
/*      */         
/*      */         if (patt373875$temp instanceof ServerLevel) {
/*      */           ServerLevel serverLevel = (ServerLevel)patt373875$temp;
/*      */           
/*      */           Item weapon = livingEntity.m_21205_().m_41720_();
/*      */           if (weapon instanceof com.pla.annoyingvillagers.item.ShadowObsidianWeaponItem || weapon instanceof com.pla.annoyingvillagers.item.ObsidianWeaponItem) {
/*      */             BlockState obsidian;
/*      */             if (weapon instanceof com.pla.annoyingvillagers.item.ShadowObsidianWeaponItem) {
/*      */               obsidian = (BlockState)((Block)AnnoyingVillagersModBlocks.SHADOW_OBSIDIAN_BLOCK.get()).m_49966_().m_61124_((Property)ShadowObsidianBlock.FROM_PLAYER, Boolean.valueOf(livingEntity instanceof Player));
/*      */             } else {
/*      */               obsidian = (BlockState)((Block)AnnoyingVillagersModBlocks.OBSIDIAN_BLOCK.get()).m_49966_().m_61124_((Property)ObsidianBlock.FROM_PLAYER, Boolean.valueOf(livingEntity instanceof Player));
/*      */             } 
/*      */             HerobrineUtil.summonObsidianBlocksInfrontOf(serverLevel, livingEntity, obsidian, 3, ((HumanoidArmature)Armatures.BIPED.get()).toolL);
/*      */           } else if (livingEntity.m_21206_().m_41720_() instanceof com.pla.annoyingvillagers.item.ShadowObsidianSwordItem) {
/*      */             HerobrineUtil.summonShadowObsidianMiddlePillarShootToward(serverLevel, (Entity)livingEntity, 4, ((HumanoidArmature)Armatures.BIPED.get()).toolL);
/*      */           } else if (weapon instanceof com.pla.annoyingvillagers.item.ShadowObsidianPillarItem) {
/*      */             HerobrineUtil.summonShadowObsidianShortPillarShootToward(serverLevel, (Entity)livingEntity, 4, ((HumanoidArmature)Armatures.BIPED.get()).toolL);
/*      */           } 
/*      */         } 
/*      */       });
/* 3981 */     SUMMON_6_OBSIDIAN_HAND_LEFT = ((livingEntityPatch, staticAnimation, object) -> {
/*      */         LivingEntity livingEntity = (LivingEntity)livingEntityPatch.getOriginal();
/*      */         
/*      */         Level patt375824$temp = livingEntity.m_9236_();
/*      */         
/*      */         if (patt375824$temp instanceof ServerLevel) {
/*      */           ServerLevel serverLevel = (ServerLevel)patt375824$temp;
/*      */           
/*      */           Item weapon = livingEntity.m_21205_().m_41720_();
/*      */           if (weapon instanceof com.pla.annoyingvillagers.item.ShadowObsidianWeaponItem || weapon instanceof com.pla.annoyingvillagers.item.ObsidianWeaponItem) {
/*      */             BlockState obsidian;
/*      */             if (weapon instanceof com.pla.annoyingvillagers.item.ShadowObsidianWeaponItem) {
/*      */               obsidian = (BlockState)((Block)AnnoyingVillagersModBlocks.SHADOW_OBSIDIAN_BLOCK.get()).m_49966_().m_61124_((Property)ShadowObsidianBlock.FROM_PLAYER, Boolean.valueOf(livingEntity instanceof Player));
/*      */             } else {
/*      */               obsidian = (BlockState)((Block)AnnoyingVillagersModBlocks.OBSIDIAN_BLOCK.get()).m_49966_().m_61124_((Property)ObsidianBlock.FROM_PLAYER, Boolean.valueOf(livingEntity instanceof Player));
/*      */             } 
/*      */             HerobrineUtil.summonObsidianBlocksInfrontOf(serverLevel, livingEntity, obsidian, 6, ((HumanoidArmature)Armatures.BIPED.get()).toolL);
/*      */           } else if (livingEntity.m_21206_().m_41720_() instanceof com.pla.annoyingvillagers.item.ShadowObsidianSwordItem) {
/*      */             HerobrineUtil.summonShadowObsidianMiddlePillarShootToward(serverLevel, (Entity)livingEntity, 7, ((HumanoidArmature)Armatures.BIPED.get()).toolL);
/*      */           } else if (weapon instanceof com.pla.annoyingvillagers.item.ShadowObsidianPillarItem) {
/*      */             HerobrineUtil.summonShadowObsidianShortPillarShootToward(serverLevel, (Entity)livingEntity, 7, ((HumanoidArmature)Armatures.BIPED.get()).toolL);
/*      */           } 
/*      */         } 
/*      */       });
/* 4005 */     SUMMON_6_OBSIDIAN_HAND_RIGHT = ((livingEntityPatch, staticAnimation, object) -> {
/*      */         LivingEntity livingEntity = (LivingEntity)livingEntityPatch.getOriginal();
/*      */         
/*      */         Level patt377774$temp = livingEntity.m_9236_();
/*      */         
/*      */         if (patt377774$temp instanceof ServerLevel) {
/*      */           ServerLevel serverLevel = (ServerLevel)patt377774$temp;
/*      */           
/*      */           Item weapon = livingEntity.m_21205_().m_41720_();
/*      */           if (weapon instanceof com.pla.annoyingvillagers.item.ShadowObsidianWeaponItem || weapon instanceof com.pla.annoyingvillagers.item.ObsidianWeaponItem) {
/*      */             BlockState obsidian;
/*      */             if (weapon instanceof com.pla.annoyingvillagers.item.ShadowObsidianWeaponItem) {
/*      */               obsidian = (BlockState)((Block)AnnoyingVillagersModBlocks.SHADOW_OBSIDIAN_BLOCK.get()).m_49966_().m_61124_((Property)ShadowObsidianBlock.FROM_PLAYER, Boolean.valueOf(livingEntity instanceof Player));
/*      */             } else {
/*      */               obsidian = (BlockState)((Block)AnnoyingVillagersModBlocks.OBSIDIAN_BLOCK.get()).m_49966_().m_61124_((Property)ObsidianBlock.FROM_PLAYER, Boolean.valueOf(livingEntity instanceof Player));
/*      */             } 
/*      */             HerobrineUtil.summonObsidianBlocksInfrontOf(serverLevel, livingEntity, obsidian, 6, ((HumanoidArmature)Armatures.BIPED.get()).toolR);
/*      */           } else if (weapon instanceof com.pla.annoyingvillagers.item.ShadowObsidianPillarItem) {
/*      */             HerobrineUtil.summonShadowObsidianShortPillarShootToward(serverLevel, (Entity)livingEntity, 7, ((HumanoidArmature)Armatures.BIPED.get()).toolR);
/*      */           } else if (livingEntity.m_21206_().m_41720_() instanceof com.pla.annoyingvillagers.item.ShadowObsidianSwordItem) {
/*      */             HerobrineUtil.summonShadowObsidianMiddlePillarShootToward(serverLevel, (Entity)livingEntity, 7, ((HumanoidArmature)Armatures.BIPED.get()).toolR);
/*      */           } 
/*      */         } 
/*      */       });
/* 4029 */     SUMMON_6_OBSIDIAN_LEG_RIGHT = ((livingEntityPatch, staticAnimation, object) -> {
/*      */         LivingEntity livingEntity = (LivingEntity)livingEntityPatch.getOriginal();
/*      */         
/*      */         Level patt379723$temp = livingEntity.m_9236_();
/*      */         
/*      */         if (patt379723$temp instanceof ServerLevel) {
/*      */           ServerLevel serverLevel = (ServerLevel)patt379723$temp;
/*      */           
/*      */           Item weapon = livingEntity.m_21205_().m_41720_();
/*      */           if (weapon instanceof com.pla.annoyingvillagers.item.ShadowObsidianWeaponItem || weapon instanceof com.pla.annoyingvillagers.item.ObsidianWeaponItem) {
/*      */             BlockState obsidian;
/*      */             if (weapon instanceof com.pla.annoyingvillagers.item.ShadowObsidianWeaponItem) {
/*      */               obsidian = (BlockState)((Block)AnnoyingVillagersModBlocks.SHADOW_OBSIDIAN_BLOCK.get()).m_49966_().m_61124_((Property)ShadowObsidianBlock.FROM_PLAYER, Boolean.valueOf(livingEntity instanceof Player));
/*      */             } else {
/*      */               obsidian = (BlockState)((Block)AnnoyingVillagersModBlocks.OBSIDIAN_BLOCK.get()).m_49966_().m_61124_((Property)ObsidianBlock.FROM_PLAYER, Boolean.valueOf(livingEntity instanceof Player));
/*      */             } 
/*      */             HerobrineUtil.summonObsidianBlocksInfrontOf(serverLevel, livingEntity, obsidian, 6, ((HumanoidArmature)Armatures.BIPED.get()).legR);
/*      */           } else if (weapon instanceof com.pla.annoyingvillagers.item.ShadowObsidianPillarItem) {
/*      */             HerobrineUtil.summonShadowObsidianShortPillarShootToward(serverLevel, (Entity)livingEntity, 7, ((HumanoidArmature)Armatures.BIPED.get()).legR);
/*      */           } 
/*      */         } 
/*      */       });
/* 4051 */     SUMMON_OBSIDIAN_PILLAR = ((livingEntityPatch, staticAnimation, object) -> {
/*      */         LivingEntity livingEntity = (LivingEntity)livingEntityPatch.getOriginal();
/*      */         
/*      */         Level patt381404$temp = livingEntity.m_9236_();
/*      */         
/*      */         if (patt381404$temp instanceof ServerLevel) {
/*      */           ServerLevel serverLevel = (ServerLevel)patt381404$temp;
/*      */           
/*      */           Item weapon = livingEntity.m_21205_().m_41720_();
/*      */           if (weapon instanceof com.pla.annoyingvillagers.item.ShadowObsidianWeaponItem || weapon instanceof com.pla.annoyingvillagers.item.ObsidianWeaponItem) {
/*      */             BlockState obsidian;
/*      */             if (weapon instanceof com.pla.annoyingvillagers.item.ShadowObsidianWeaponItem) {
/*      */               obsidian = (BlockState)((Block)AnnoyingVillagersModBlocks.SHADOW_OBSIDIAN_BLOCK.get()).m_49966_().m_61124_((Property)ShadowObsidianBlock.FROM_PLAYER, Boolean.valueOf(livingEntity instanceof Player));
/*      */             } else {
/*      */               obsidian = (BlockState)((Block)AnnoyingVillagersModBlocks.OBSIDIAN_BLOCK.get()).m_49966_().m_61124_((Property)ObsidianBlock.FROM_PLAYER, Boolean.valueOf(livingEntity instanceof Player));
/*      */             } 
/*      */             HerobrineUtil.summonObsidianPillar(serverLevel, livingEntity, obsidian);
/*      */           } else if (weapon instanceof com.pla.annoyingvillagers.item.ShadowObsidianPillarItem) {
/*      */             HerobrineUtil.summonShadowObsidianLongPillarShootToward(serverLevel, (Entity)livingEntity);
/*      */           } 
/*      */         } 
/*      */       });
/* 4073 */     SUMMON_OBSIDIAN_WALL = ((livingEntityPatch, staticAnimation, object) -> {
/*      */         LivingEntity livingEntity = (LivingEntity)livingEntityPatch.getOriginal();
/*      */         
/*      */         Level patt383011$temp = livingEntity.m_9236_();
/*      */         
/*      */         if (patt383011$temp instanceof ServerLevel) {
/*      */           ServerLevel serverLevel = (ServerLevel)patt383011$temp;
/*      */           
/*      */           Item weapon = livingEntity.m_21205_().m_41720_();
/*      */           
/*      */           if (weapon instanceof com.pla.annoyingvillagers.item.ShadowObsidianWeaponItem || weapon instanceof com.pla.annoyingvillagers.item.ObsidianWeaponItem) {
/*      */             BlockState obsidian;
/*      */             if (weapon instanceof com.pla.annoyingvillagers.item.ShadowObsidianWeaponItem) {
/*      */               obsidian = (BlockState)((Block)AnnoyingVillagersModBlocks.SHADOW_OBSIDIAN_BLOCK.get()).m_49966_().m_61124_((Property)ShadowObsidianBlock.FROM_PLAYER, Boolean.valueOf(livingEntity instanceof Player));
/*      */             } else {
/*      */               obsidian = (BlockState)((Block)AnnoyingVillagersModBlocks.OBSIDIAN_BLOCK.get()).m_49966_().m_61124_((Property)ObsidianBlock.FROM_PLAYER, Boolean.valueOf(livingEntity instanceof Player));
/*      */             } 
/*      */             HerobrineUtil.summonObsidianWall(serverLevel, livingEntity, obsidian);
/*      */           } else if (weapon instanceof com.pla.annoyingvillagers.item.ShadowObsidianPillarItem || weapon instanceof com.pla.annoyingvillagers.item.ShadowObsidianSwordItem) {
/*      */             HerobrineUtil.summonShadowObsidianLongPillarDefense(serverLevel, (Entity)livingEntity);
/*      */           } 
/*      */         } 
/*      */       });
/* 4096 */     SUMMON_OBSIDIAN_CIRCLE = ((livingEntityPatch, staticAnimation, object) -> {
/*      */         LivingEntity livingEntity = (LivingEntity)livingEntityPatch.getOriginal();
/*      */         Level patt384661$temp = livingEntity.m_9236_();
/*      */         if (patt384661$temp instanceof ServerLevel) {
/*      */           ServerLevel serverLevel = (ServerLevel)patt384661$temp;
/*      */           HerobrineUtil.summonShadowObsidianLongPillarCircle(serverLevel, (Entity)livingEntity, livingEntity.m_20097_());
/*      */           if (livingEntity.m_21205_().m_41720_() instanceof com.pla.annoyingvillagers.item.ShadowObsidianPillarItem) {
/*      */             HerobrineUtil.summonShadowObsidianLongPillarShootToward(serverLevel, (Entity)livingEntity);
/*      */           }
/*      */         } 
/*      */       });
/* 4107 */     SUMMON_OBSIDIAN_CROSS = ((livingEntityPatch, staticAnimation, object) -> {
/*      */         LivingEntity livingEntity = (LivingEntity)livingEntityPatch.getOriginal();
/*      */         
/*      */         Level patt385388$temp = livingEntity.m_9236_();
/*      */         
/*      */         if (patt385388$temp instanceof ServerLevel) {
/*      */           ServerLevel serverLevel = (ServerLevel)patt385388$temp;
/*      */           
/*      */           Item weapon = livingEntity.m_21205_().m_41720_();
/*      */           
/*      */           if (weapon instanceof com.pla.annoyingvillagers.item.ShadowObsidianWeaponItem || weapon instanceof com.pla.annoyingvillagers.item.ObsidianWeaponItem) {
/*      */             BlockState obsidian;
/*      */             
/*      */             if (weapon instanceof com.pla.annoyingvillagers.item.ShadowObsidianWeaponItem) {
/*      */               obsidian = (BlockState)((Block)AnnoyingVillagersModBlocks.SHADOW_OBSIDIAN_BLOCK.get()).m_49966_().m_61124_((Property)ShadowObsidianBlock.FROM_PLAYER, Boolean.valueOf(livingEntity instanceof Player));
/*      */             } else {
/*      */               obsidian = (BlockState)((Block)AnnoyingVillagersModBlocks.OBSIDIAN_BLOCK.get()).m_49966_().m_61124_((Property)ObsidianBlock.FROM_PLAYER, Boolean.valueOf(livingEntity instanceof Player));
/*      */             } 
/*      */             HerobrineUtil.summonObsidianCross(serverLevel, livingEntity, obsidian);
/*      */           } else if (weapon instanceof com.pla.annoyingvillagers.item.ShadowObsidianPillarItem) {
/*      */             if (livingEntity instanceof Player) {
/*      */               HerobrineUtil.summonShadowObsidianLongPillarDefenseWide(serverLevel, (Entity)livingEntity);
/*      */             }
/*      */           } 
/*      */         } 
/*      */       });
/* 4133 */     SUMMON_OBSIDIAN_CROSS_FIX_DELAY_SHADOW_HEROBRINE = ((livingEntityPatch, staticAnimation, object) -> {
/*      */         LivingEntity livingEntity = (LivingEntity)livingEntityPatch.getOriginal();
/*      */         Item weapon = livingEntity.m_21205_().m_41720_();
/*      */         Level patt387254$temp = livingEntity.m_9236_();
/*      */         if (patt387254$temp instanceof ServerLevel) {
/*      */           ServerLevel serverLevel = (ServerLevel)patt387254$temp;
/*      */           if (!(livingEntity instanceof Player) && weapon instanceof com.pla.annoyingvillagers.item.ShadowObsidianPillarItem) {
/*      */             HerobrineUtil.summonShadowObsidianLongPillarDefenseWide(serverLevel, (Entity)livingEntity);
/*      */           }
/*      */         } 
/*      */       });
/* 4144 */     SUMMON_OBSIDIAN_SMALL_CROSS = ((livingEntityPatch, staticAnimation, object) -> {
/*      */         LivingEntity livingEntity = (LivingEntity)livingEntityPatch.getOriginal();
/*      */         
/*      */         Level patt387859$temp = livingEntity.m_9236_();
/*      */         
/*      */         if (patt387859$temp instanceof ServerLevel) {
/*      */           BlockState obsidian;
/*      */           
/*      */           ServerLevel serverLevel = (ServerLevel)patt387859$temp;
/*      */           
/*      */           Item weapon = livingEntity.m_21205_().m_41720_();
/*      */           
/*      */           if (weapon instanceof com.pla.annoyingvillagers.item.ShadowObsidianWeaponItem) {
/*      */             obsidian = (BlockState)((Block)AnnoyingVillagersModBlocks.SHADOW_OBSIDIAN_BLOCK.get()).m_49966_().m_61124_((Property)ShadowObsidianBlock.FROM_PLAYER, Boolean.valueOf(livingEntity instanceof Player));
/*      */           } else if (weapon instanceof com.pla.annoyingvillagers.item.ShadowObsidianPillarItem) {
/*      */             obsidian = (BlockState)((BlockState)((Block)AnnoyingVillagersModBlocks.SHADOW_OBSIDIAN_LONG_PILLAR.get()).m_49966_().m_61124_((Property)ObsidianBlock.FROM_PLAYER, Boolean.valueOf(livingEntity instanceof Player))).m_61124_((Property)BlockStateProperties.f_61374_, (Comparable)livingEntity.m_6350_());
/*      */           } else {
/*      */             obsidian = (BlockState)((Block)AnnoyingVillagersModBlocks.OBSIDIAN_BLOCK.get()).m_49966_().m_61124_((Property)ObsidianBlock.FROM_PLAYER, Boolean.valueOf(livingEntity instanceof Player));
/*      */           } 
/*      */           
/*      */           HerobrineUtil.summonObsidianSmallCross(serverLevel, livingEntity, obsidian);
/*      */         } 
/*      */       });
/*      */     
/* 4168 */     THROW_OBSIDIAN = ((livingEntityPatch, staticAnimation, object) -> {
/*      */         LivingEntity livingEntity = (LivingEntity)livingEntityPatch.getOriginal();
/*      */         
/*      */         Level patt389549$temp = livingEntity.m_9236_();
/*      */         
/*      */         if (patt389549$temp instanceof ServerLevel) {
/*      */           BlockState obsidian;
/*      */           
/*      */           ServerLevel serverLevel = (ServerLevel)patt389549$temp;
/*      */           
/*      */           Item weapon = livingEntity.m_21205_().m_41720_();
/*      */           
/*      */           if (weapon instanceof com.pla.annoyingvillagers.item.ShadowObsidianWeaponItem) {
/*      */             obsidian = (BlockState)((Block)AnnoyingVillagersModBlocks.SHADOW_OBSIDIAN_BLOCK.get()).m_49966_().m_61124_((Property)ShadowObsidianBlock.FROM_PLAYER, Boolean.valueOf(livingEntity instanceof Player));
/*      */           } else if (weapon instanceof com.pla.annoyingvillagers.item.ShadowObsidianSwordItem) {
/*      */             obsidian = (BlockState)((Block)AnnoyingVillagersModBlocks.SHADOW_OBSIDIAN_MIDDLE_PILLAR.get()).m_49966_().m_61124_((Property)ObsidianBlock.FROM_PLAYER, Boolean.valueOf(livingEntity instanceof Player));
/*      */           } else {
/*      */             obsidian = (BlockState)((Block)AnnoyingVillagersModBlocks.OBSIDIAN_BLOCK.get()).m_49966_().m_61124_((Property)ObsidianBlock.FROM_PLAYER, Boolean.valueOf(livingEntity instanceof Player));
/*      */           } 
/*      */           LivingEntity attacker = (LivingEntity)livingEntityPatch.getOriginal();
/*      */           Vec3 to = attacker.m_146892_().m_82549_(attacker.m_20154_().m_82490_(16.0D));
/*      */           if (attacker instanceof Mob) {
/*      */             Mob mob = (Mob)attacker;
/*      */             if (mob.m_5448_() != null) {
/*      */               to = mob.m_5448_().m_20299_(1.0F);
/*      */             }
/*      */           } 
/*      */           BlockProjectileEntity throwingObsidian = new BlockProjectileEntity(attacker.m_9236_(), attacker, obsidian);
/*      */           serverLevel.m_7967_((Entity)throwingObsidian);
/*      */           Vec3 dir = to.m_82546_(throwingObsidian.m_20182_());
/*      */           if (dir.m_82556_() < 1.0E-6D) {
/*      */             dir = attacker.m_20154_();
/*      */           }
/*      */           Vec3 vel = dir.m_82541_().m_82490_(2.0D);
/*      */           throwingObsidian.m_20256_(vel);
/*      */         } 
/*      */       });
/* 4205 */     THROW_OBSIDIAN_OFFHAND = ((livingEntityPatch, staticAnimation, object) -> {
/*      */         LivingEntity livingEntity = (LivingEntity)livingEntityPatch.getOriginal();
/*      */         Level patt392023$temp = livingEntity.m_9236_();
/*      */         if (patt392023$temp instanceof ServerLevel) {
/*      */           BlockState obsidian;
/*      */           ServerLevel serverLevel = (ServerLevel)patt392023$temp;
/*      */           Vec3 jointVec = EpicfightUtil.getJointWithTranslation((Entity)livingEntity, new Vec3f(0.0F, 0.0F, 0.0F), ((HumanoidArmature)Armatures.BIPED.get()).toolL, 2.0F, 0.0D);
/*      */           Item weapon = livingEntity.m_21205_().m_41720_();
/*      */           if (weapon instanceof com.pla.annoyingvillagers.item.ShadowObsidianWeaponItem) {
/*      */             obsidian = (BlockState)((Block)AnnoyingVillagersModBlocks.SHADOW_OBSIDIAN_BLOCK.get()).m_49966_().m_61124_((Property)ShadowObsidianBlock.FROM_PLAYER, Boolean.valueOf(livingEntity instanceof Player));
/*      */           } else if (weapon instanceof com.pla.annoyingvillagers.item.ShadowObsidianSwordItem) {
/*      */             obsidian = (BlockState)((Block)AnnoyingVillagersModBlocks.SHADOW_OBSIDIAN_MIDDLE_PILLAR.get()).m_49966_().m_61124_((Property)ObsidianBlock.FROM_PLAYER, Boolean.valueOf(livingEntity instanceof Player));
/*      */           } else {
/*      */             obsidian = (BlockState)((Block)AnnoyingVillagersModBlocks.OBSIDIAN_BLOCK.get()).m_49966_().m_61124_((Property)ObsidianBlock.FROM_PLAYER, Boolean.valueOf(livingEntity instanceof Player));
/*      */           } 
/*      */           LivingEntity attacker = (LivingEntity)livingEntityPatch.getOriginal();
/*      */           Vec3 to = attacker.m_146892_().m_82549_(attacker.m_20154_().m_82490_(16.0D));
/*      */           if (attacker instanceof Mob) {
/*      */             Mob mob = (Mob)attacker;
/*      */             if (mob.m_5448_() != null) {
/*      */               to = mob.m_5448_().m_20299_(1.0F);
/*      */             }
/*      */           } 
/*      */           BlockProjectileEntity throwingObsidian = new BlockProjectileEntity(attacker.m_9236_(), attacker, obsidian);
/*      */           serverLevel.m_7967_((Entity)throwingObsidian);
/*      */           if (jointVec != null) {
/*      */             throwingObsidian.m_20219_(jointVec);
/*      */           }
/*      */           Vec3 dir = to.m_82546_(throwingObsidian.m_20182_());
/*      */           if (dir.m_82556_() < 1.0E-6D) {
/*      */             dir = attacker.m_20154_();
/*      */           }
/*      */           Vec3 vel = dir.m_82541_().m_82490_(2.0D);
/*      */           throwingObsidian.m_20256_(vel);
/*      */         } 
/*      */       });
/*      */   }
/*      */ 
/*      */ 
/*      */ 
/*      */ 
/*      */ 
/*      */ 
/*      */ 
/*      */ 
/*      */   
/*      */   public static final AnimationEvent.E0 SLEDGEHAMMER_SHOOT = (livingEntityPatch, staticAnimation, object) -> {
/*      */       // Byte code:
/*      */       //   0: aload_0
/*      */       //   1: invokevirtual getOriginal : ()Lnet/minecraft/world/entity/Entity;
/*      */       //   4: checkcast net/minecraft/world/entity/LivingEntity
/*      */       //   7: invokevirtual m_9236_ : ()Lnet/minecraft/world/level/Level;
/*      */       //   10: astore #4
/*      */       //   12: aload #4
/*      */       //   14: instanceof net/minecraft/server/level/ServerLevel
/*      */       //   17: ifeq -> 284
/*      */       //   20: aload #4
/*      */       //   22: checkcast net/minecraft/server/level/ServerLevel
/*      */       //   25: astore_3
/*      */       //   26: aload_0
/*      */       //   27: invokevirtual getOriginal : ()Lnet/minecraft/world/entity/Entity;
/*      */       //   30: checkcast net/minecraft/world/entity/LivingEntity
/*      */       //   33: astore #4
/*      */       //   35: aconst_null
/*      */       //   36: astore #5
/*      */       //   38: aload #4
/*      */       //   40: instanceof net/minecraft/world/entity/Mob
/*      */       //   43: ifeq -> 75
/*      */       //   46: aload #4
/*      */       //   48: checkcast net/minecraft/world/entity/Mob
/*      */       //   51: astore #6
/*      */       //   53: aload #6
/*      */       //   55: invokevirtual m_5448_ : ()Lnet/minecraft/world/entity/LivingEntity;
/*      */       //   58: ifnull -> 75
/*      */       //   61: aload #6
/*      */       //   63: invokevirtual m_5448_ : ()Lnet/minecraft/world/entity/LivingEntity;
/*      */       //   66: fconst_1
/*      */       //   67: invokevirtual m_20299_ : (F)Lnet/minecraft/world/phys/Vec3;
/*      */       //   70: astore #5
/*      */       //   72: goto -> 124
/*      */       //   75: aload #4
/*      */       //   77: instanceof net/minecraft/world/entity/player/Player
/*      */       //   80: ifeq -> 124
/*      */       //   83: aload #4
/*      */       //   85: checkcast net/minecraft/world/entity/player/Player
/*      */       //   88: astore #7
/*      */       //   90: aload #7
/*      */       //   92: fconst_1
/*      */       //   93: invokevirtual m_20299_ : (F)Lnet/minecraft/world/phys/Vec3;
/*      */       //   96: astore #8
/*      */       //   98: aload #7
/*      */       //   100: invokevirtual m_20154_ : ()Lnet/minecraft/world/phys/Vec3;
/*      */       //   103: astore #9
/*      */       //   105: ldc2_w 64.0
/*      */       //   108: dstore #10
/*      */       //   110: aload #8
/*      */       //   112: aload #9
/*      */       //   114: dload #10
/*      */       //   116: invokevirtual m_82490_ : (D)Lnet/minecraft/world/phys/Vec3;
/*      */       //   119: invokevirtual m_82549_ : (Lnet/minecraft/world/phys/Vec3;)Lnet/minecraft/world/phys/Vec3;
/*      */       //   122: astore #5
/*      */       //   124: new com/pla/annoyingvillagers/entity/ObsidianSledgehammerProjectileEntity
/*      */       //   127: dup
/*      */       //   128: getstatic com/pla/annoyingvillagers/init/AnnoyingVillagersModEntities.OBSIDIAN_SLEDGEHAMMER_PROJECTILE : Lnet/minecraftforge/registries/RegistryObject;
/*      */       //   131: invokevirtual get : ()Ljava/lang/Object;
/*      */       //   134: checkcast net/minecraft/world/entity/EntityType
/*      */       //   137: aload_3
/*      */       //   138: invokespecial <init> : (Lnet/minecraft/world/entity/EntityType;Lnet/minecraft/world/level/Level;)V
/*      */       //   141: astore #6
/*      */       //   143: aload_0
/*      */       //   144: invokevirtual getOriginal : ()Lnet/minecraft/world/entity/Entity;
/*      */       //   147: new yesman/epicfight/api/utils/math/Vec3f
/*      */       //   150: dup
/*      */       //   151: fconst_0
/*      */       //   152: fconst_0
/*      */       //   153: fconst_0
/*      */       //   154: invokespecial <init> : (FFF)V
/*      */       //   157: getstatic yesman/epicfight/gameasset/Armatures.BIPED : Lyesman/epicfight/gameasset/Armatures$ArmatureAccessor;
/*      */       //   160: invokevirtual get : ()Lyesman/epicfight/api/model/Armature;
/*      */       //   163: checkcast yesman/epicfight/model/armature/HumanoidArmature
/*      */       //   166: getfield toolR : Lyesman/epicfight/api/animation/Joint;
/*      */       //   169: fconst_1
/*      */       //   170: dconst_0
/*      */       //   171: invokestatic getJointWithTranslation : (Lnet/minecraft/world/entity/Entity;Lyesman/epicfight/api/utils/math/Vec3f;Lyesman/epicfight/api/animation/Joint;FD)Lnet/minecraft/world/phys/Vec3;
/*      */       //   174: astore #7
/*      */       //   176: aload #7
/*      */       //   178: ifnull -> 284
/*      */       //   181: aload #5
/*      */       //   183: ifnull -> 284
/*      */       //   186: aload #6
/*      */       //   188: aload #7
/*      */       //   190: getfield f_82479_ : D
/*      */       //   193: aload #7
/*      */       //   195: getfield f_82480_ : D
/*      */       //   198: aload #7
/*      */       //   200: getfield f_82481_ : D
/*      */       //   203: fconst_0
/*      */       //   204: fconst_0
/*      */       //   205: invokevirtual m_7678_ : (DDDFF)V
/*      */       //   208: aload #6
/*      */       //   210: new net/minecraft/world/phys/Vec3
/*      */       //   213: dup
/*      */       //   214: aload #5
/*      */       //   216: getfield f_82479_ : D
/*      */       //   219: aload #5
/*      */       //   221: getfield f_82480_ : D
/*      */       //   224: aload #5
/*      */       //   226: getfield f_82481_ : D
/*      */       //   229: invokespecial <init> : (DDD)V
/*      */       //   232: invokevirtual setPosToAim : (Lnet/minecraft/world/phys/Vec3;)V
/*      */       //   235: aload #6
/*      */       //   237: iconst_1
/*      */       //   238: invokevirtual m_20331_ : (Z)V
/*      */       //   241: aload #6
/*      */       //   243: getstatic com/pla/annoyingvillagers/init/AnnoyingVillagersModSounds.METAL_HIT : Lnet/minecraftforge/registries/RegistryObject;
/*      */       //   246: invokevirtual get : ()Ljava/lang/Object;
/*      */       //   249: checkcast net/minecraft/sounds/SoundEvent
/*      */       //   252: fconst_1
/*      */       //   253: fconst_1
/*      */       //   254: invokevirtual m_5496_ : (Lnet/minecraft/sounds/SoundEvent;FF)V
/*      */       //   257: aload #6
/*      */       //   259: aload #4
/*      */       //   261: invokevirtual setOwner : (Lnet/minecraft/world/entity/LivingEntity;)V
/*      */       //   264: aload_1
/*      */       //   265: getstatic com/pla/annoyingvillagers/gameasset/AVAnimations.SLEDGEHAMMER_SOLAR_AUTO_3 : Lyesman/epicfight/api/animation/AnimationManager$AnimationAccessor;
/*      */       //   268: if_acmpne -> 277
/*      */       //   271: aload #6
/*      */       //   273: iconst_1
/*      */       //   274: invokevirtual setShouldStun : (Z)V
/*      */       //   277: aload_3
/*      */       //   278: aload #6
/*      */       //   280: invokevirtual m_7967_ : (Lnet/minecraft/world/entity/Entity;)Z
/*      */       //   283: pop
/*      */       //   284: return
/*      */       // Line number table:
/*      */       //   Java source line number -> byte code offset
/*      */       //   #4251	-> 0
/*      */       //   #4252	-> 26
/*      */       //   #4254	-> 35
/*      */       //   #4256	-> 38
/*      */       //   #4257	-> 61
/*      */       //   #4258	-> 75
/*      */       //   #4259	-> 90
/*      */       //   #4260	-> 98
/*      */       //   #4261	-> 105
/*      */       //   #4262	-> 110
/*      */       //   #4265	-> 124
/*      */       //   #4266	-> 143
/*      */       //   #4267	-> 160
/*      */       //   #4266	-> 171
/*      */       //   #4268	-> 176
/*      */       //   #4269	-> 186
/*      */       //   #4270	-> 208
/*      */       //   #4271	-> 235
/*      */       //   #4272	-> 241
/*      */       //   #4273	-> 257
/*      */       //   #4274	-> 264
/*      */       //   #4275	-> 271
/*      */       //   #4277	-> 277
/*      */       //   #4280	-> 284
/*      */       // Local variable table:
/*      */       //   start	length	slot	name	descriptor
/*      */       //   12	14	4	patt394818$temp	Lnet/minecraft/world/level/Level;
/*      */       //   53	22	6	mob	Lnet/minecraft/world/entity/Mob;
/*      */       //   98	26	8	playerEyePosition	Lnet/minecraft/world/phys/Vec3;
/*      */       //   105	19	9	playerLookDirection	Lnet/minecraft/world/phys/Vec3;
/*      */       //   110	14	10	aimDistance	D
/*      */       //   90	34	7	player	Lnet/minecraft/world/entity/player/Player;
/*      */       //   35	249	4	shooterEntity	Lnet/minecraft/world/entity/LivingEntity;
/*      */       //   38	246	5	aimPosition	Lnet/minecraft/world/phys/Vec3;
/*      */       //   143	141	6	obsidianSledgehammerProjectileEntity	Lcom/pla/annoyingvillagers/entity/ObsidianSledgehammerProjectileEntity;
/*      */       //   176	108	7	hammerPos	Lnet/minecraft/world/phys/Vec3;
/*      */       //   26	258	3	serverLevel	Lnet/minecraft/server/level/ServerLevel;
/*      */       //   0	285	0	livingEntityPatch	Lyesman/epicfight/world/capabilities/entitypatch/LivingEntityPatch;
/*      */       //   0	285	1	staticAnimation	Lyesman/epicfight/api/asset/AssetAccessor;
/*      */       //   0	285	2	object	Lyesman/epicfight/api/animation/property/AnimationParameters;
/*      */     };
/*      */ 
/*      */ 
/*      */ 
/*      */ 
/*      */ 
/*      */ 
/*      */ 
/*      */   
/*      */   public static final AnimationEvent.E0 SHOCK_WAVE;
/*      */ 
/*      */ 
/*      */ 
/*      */ 
/*      */ 
/*      */ 
/*      */ 
/*      */   
/*      */   public static final AnimationEvent.E0 END_ATTACK;
/*      */ 
/*      */ 
/*      */ 
/*      */ 
/*      */ 
/*      */ 
/*      */ 
/*      */   
/*      */   static {
/* 4281 */     SHOCK_WAVE = ((livingEntityPatch, staticAnimation, object) -> {
/*      */         Vec3 legendarySwordPos = EpicfightUtil.getJointWithTranslation(livingEntityPatch.getOriginal(), new Vec3f(0.0F, 0.0F, 0.0F), ((HumanoidArmature)Armatures.BIPED.get()).toolR, 1.5F, 0.0D);
/*      */         int MAX_SHOCKWAVE_RADIUS = 6;
/*      */         int TICKS_BETWEEN_LAYERS = 2;
/*      */         for (int radius = 1; radius <= 6; radius++) {
/*      */           int delayTicks = (radius - 1) * 2;
/*      */           final int ringRadius = radius;
/*      */           if (legendarySwordPos == null) {
/*      */             return;
/*      */           }
/*      */           final BlockPos finalVec = BlockPos.m_274446_((Position)legendarySwordPos);
/*      */           new DelayedTask(delayTicks)
/*      */             {
/*      */               public void run()
/*      */               {
/* 4296 */                 ShockwaveUtil.spawnCircleRing((ServerLevel)((LivingEntity)livingEntityPatch.getOriginal()).m_9236_(), finalVec, ringRadius, (LivingEntity)livingEntityPatch.getOriginal());
/*      */               }
/*      */             };
/*      */         } 
/*      */       });
/*      */     
/* 4302 */     END_ATTACK = ((livingentitypatch, staticAnimation, object) -> {
/*      */         if (livingentitypatch instanceof yesman.epicfight.world.capabilities.entitypatch.player.PlayerPatch) {
/*      */           livingentitypatch.playAnimationSynchronized((AssetAccessor)AVAnimations.DUAL_END, 0.1F);
/*      */         }
/*      */       });
/*      */   }
/*      */   
/*      */   public static Vec3 getFloor(LivingEntityPatch<?> livingentitypatch, Vec3f vec3f, Joint joint) {
/* 4310 */     OpenMatrix4f openmatrix4f = livingentitypatch.getArmature().getBoundTransformFor(livingentitypatch.getAnimator().getPose(1.0F), joint);
/*      */     
/* 4312 */     openmatrix4f.translate(vec3f);
/* 4313 */     OpenMatrix4f openMatrix4f1 = (new OpenMatrix4f()).rotate(-((float)Math.toRadians((((LivingEntity)livingentitypatch.getOriginal()).f_19859_ + 180.0F))), new Vec3f(0.0F, 1.0F, 0.0F));
/*      */     
/* 4315 */     OpenMatrix4f.mul(openMatrix4f1, openmatrix4f, openmatrix4f);
/* 4316 */     float f = openmatrix4f.m30 + (float)((LivingEntity)livingentitypatch.getOriginal()).m_20185_();
/* 4317 */     float f1 = openmatrix4f.m31 + (float)((LivingEntity)livingentitypatch.getOriginal()).m_20186_();
/* 4318 */     float f2 = openmatrix4f.m32 + (float)((LivingEntity)livingentitypatch.getOriginal()).m_20189_();
/*      */     
/* 4320 */     for (BlockState blockstate = ((LivingEntity)livingentitypatch.getOriginal()).m_9236_().m_8055_(new BlockPos(new Vec3i((int)f, (int)f1, (int)f2))); (blockstate.m_60734_() instanceof net.minecraft.world.level.block.BushBlock || blockstate.m_60795_()) && !blockstate.m_60713_(Blocks.f_50626_); blockstate = ((LivingEntity)livingentitypatch.getOriginal()).m_9236_().m_8055_(new BlockPos(new Vec3i((int)f, (int)f1, (int)f2)))) {
/* 4321 */       f1--;
/*      */     }
/*      */     
/* 4324 */     return new Vec3(f, f1, f2);
/*      */   }
/*      */ }


/* Location:              C:\Users\Aours\AppData\Roaming\PrismLauncher\instances\1.20.1 remake\minecraft\mods\AnnoyingVillagers-1.20.1-1.4.5.jar!\com\pla\annoyingvillagers\gameasset\AVAnimations$ReuseableEvents.class
 * Java compiler version: 17 (61.0)
 * JD-Core Version:       1.1.3
 */